Workbook

Sheet Movie Data Base by Keizar
A1: Película | B1: Año | C1: Década | D1: Duración | E1: Director | F1: IMDb | G1: Mi nota | H1: Votos | I1: País | J1: Género | K1: Subgénero | L1: VOD (04/10/2026) | M1: Sinopsis | N1: Óscars | O1: Óscar Peli | P1: Óscar Dir. | Q1: Nom. Óscar | R1: Festivales | S1: Globo Oro | T1: S&S | U1: Puntos premios | V1: Importancia histórica | W1: Rank J.Wild | X1: Top150 XXI | Y1: IMDb ID
A2: La vida es bella | B2: 1997 | C2: 1990s | D2: 116 | E2: Roberto Benigni | F2: 8.6 | G2: 9 | H2: 819784 | I2: Italia | J2: Romance | K2: Comedia | M2: Un padre utiliza humor para proteger a su hijo en un campo nazi. | N2: 3 | O2: 0 | P2: 0 | Q2: 7 | R2: 0 | S2: 0 | U2: =O2*4 + P2*2 + MAX(0,N2-O2-P2)*1 + Q2*0.2 + R2*2 + S2*1 + IF(T2="",0,IF(T2<=10,8,IF(T2<=50,6,IF(T2<=100,4,2)))) -> 4.4 | V2: La vida es bella (1997) popularizó una aproximación agridulce al Holocausto, combinando humor y tragedia de. | Y2: tt0118799
A3: El señor de los anillos: El retorno del rey | B3: 2003 | C3: 2000s | D3: 201 | E3: Peter Jackson | F3: 9 | G3: 10 | H3: 2184685 | I3: EE.UU., Nueva Zelanda | J3: Fantasía | K3: Aventura | L3: Disney+, Movistar Plus+ Ficción Total , HBO Max, HBO Max Amazon Channel | M3: La batalla final contra Sauron mientras Frodo llega al Monte del Destino. | N3: 11 | O3: 1 | P3: 1 | Q3: 11 | R3: 0 | S3: 1 | U3: =O3*4 + P3*2 + MAX(0,N3-O3-P3)*1 + Q3*0.2 + R3*2 + S3*1 + IF(T3="",0,IF(T3<=10,8,IF(T3<=50,6,IF(T3<=100,4,2)))) -> 18.2 | V3: El retorno del Rey (2003) marcó un antes y un después en la fantasía épica cinematográfica, culminando una. | Y3: tt0167260
A4: La lista de Schindler | B4: 1993 | C4: 1990s | D4: 196 | E4: Steven Spielberg | F4: 9 | H4: 1597609 | I4: EE.UU. | J4: Drama | K4: Biográfico | M4: Oskar Schindler salva a cientos de judíos durante el Holocausto. | N4: 7 | O4: 1 | P4: 1 | Q4: 12 | R4: 0 | S4: 1 | U4: =O4*4 + P4*2 + MAX(0,N4-O4-P4)*1 + Q4*0.2 + R4*2 + S4*1 + IF(T4="",0,IF(T4<=10,8,IF(T4<=50,6,IF(T4<=100,4,2)))) -> 14.4 | V4: La lista de Schindler (1993) es uno de los retratos más potentes del Holocausto, clave en la memoria. | Y4: tt0108052
A5: Pulp Fiction | B5: 1994 | C5: 1990s | D5: 154 | E5: Quentin Tarantino | F5: 8.8 | G5: 9 | H5: 2458225 | I5: EE.UU. | J5: Drama | K5: Crimen | L5: Movistar Plus+ Ficción Total , HBO Max, HBO Max Amazon Channel | M5: Historias cruzadas de sicarios, un boxeador y una cita. | N5: 1 | O5: 0 | P5: 0 | Q5: 7 | R5: 1 | S5: 0 | T5: 129 | U5: =O5*4 + P5*2 + MAX(0,N5-O5-P5)*1 + Q5*0.2 + R5*2 + S5*1 + IF(T5="",0,IF(T5<=10,8,IF(T5<=50,6,IF(T5<=100,4,2)))) -> 6.4 | V5: Popularizó la narrativa fragmentada y no lineal, el diálogo pop y revitalizó el cine independiente de los 90. | W5: TOP 30-40 | Y5: tt0110912
A6: El padrino | B6: 1972 | C6: 1970s | D6: 175 | E6: Francis F. Coppola | F6: 9.2 | G6: 9 | H6: 2247164 | I6: EE.UU. | J6: Drama | K6: Crimen | L6: Netflix, Movistar Plus+ Ficción Total , Filmin, SkyShowtime | M6: Una familia mafiosa y el hijo que no quería heredarla. | N6: 3 | O6: 1 | P6: 0 | Q6: 11 | R6: 0 | S6: 1 | T6: 12 | U6: =O6*4 + P6*2 + MAX(0,N6-O6-P6)*1 + Q6*0.2 + R6*2 + S6*1 + IF(T6="",0,IF(T6<=10,8,IF(T6<=50,6,IF(T6<=100,4,2)))) -> 15.2 | V6: El padrino (1972) fijó el canon del cine de mafia moderno, con un equilibrio perfecto entre drama familiar y. | W6: TOP 30-40 | Y6: tt0068646
A7: Cadena perpetua | B7: 1994 | C7: 1990s | D7: 142 | E7: Frank Darabont | F7: 9.3 | G7: 9 | H7: 3223946 | I7: EE.UU. | J7: Drama | L7: Prime, Movistar Plus+ Ficción Total , HBO Max, HBO Max Amazon Channel | M7: La amistad entre dos presos condenados y su lucha por la esperanza en prisión. | N7: 0 | O7: 0 | P7: 0 | Q7: 7 | R7: 0 | S7: 0 | U7: =O7*4 + P7*2 + MAX(0,N7-O7-P7)*1 + Q7*0.2 + R7*2 + S7*1 + IF(T7="",0,IF(T7<=10,8,IF(T7<=50,6,IF(T7<=100,4,2)))) -> 1.4 | V7: Cadena perpetua (1994) se ha convertido con los años en un clásico moderno sobre esperanza y amistad en la. | Y7: tt0111161
A8: Million Dollar Baby | B8: 2004 | C8: 2000s | D8: 132 | E8: Clint Eastwood | F8: 8.1 | H8: 771297 | I8: EE.UU. | J8: Drama | K8: Deportivo | L8: Prime, Movistar, Movistar Plus+ Ficción Total , HBO Max, Acontra, HBO Max Amazon Channel | M8: Un entrenador veterano forma a una boxeadora tardía. | N8: 4 | O8: 1 | P8: 1 | Q8: 7 | R8: 0 | S8: 0 | U8: =O8*4 + P8*2 + MAX(0,N8-O8-P8)*1 + Q8*0.2 + R8*2 + S8*1 + IF(T8="",0,IF(T8<=10,8,IF(T8<=50,6,IF(T8<=100,4,2)))) -> 9.4 | V8: Ganó cuatro Óscars y reabrió el debate sobre la eutanasia. | X8: 66 | Y8: tt0405159
A9: American History X | B9: 1998 | C9: 1990s | D9: 119 | E9: Tony Kaye | F9: 8.5 | G9: 8 | H9: 1282562 | I9: EE.UU. | J9: Drama | K9: Carcelario | L9: 3Cat | M9: Un neonazi reformado intenta evitar que su hermano siga sus pasos. | N9: 0 | O9: 0 | P9: 0 | Q9: 1 | R9: 0 | S9: 0 | U9: =O9*4 + P9*2 + MAX(0,N9-O9-P9)*1 + Q9*0.2 + R9*2 + S9*1 + IF(T9="",0,IF(T9<=10,8,IF(T9<=50,6,IF(T9<=100,4,2)))) -> 0.2 | V9: American History X (1998) es una de las representaciones más intensas del odio racial y la radicalización. | Y9: tt0120586
A10: El pianista | B10: 2002 | C10: 2000s | D10: 150 | E10: Roman Polanski | F10: 8.5 | G10: 8 | H10: 1020984 | I10: Francia, Polonia | J10: Musical | K10: Biográfico | L10: Prime, Disney+, Movistar, Movistar Plus+ Ficción Total , FlixOlé, FlixOlé Amazon Channel | M10: Un pianista judío lucha por sobrevivir durante el Holocausto. | N10: 3 | O10: 0 | P10: 1 | Q10: 7 | R10: 1 | S10: 0 | U10: =O10*4 + P10*2 + MAX(0,N10-O10-P10)*1 + Q10*0.2 + R10*2 + S10*1 + IF(T10="",0,IF(T10<=10,8,IF(T10<=50,6,IF(T10<=100,4,2)))) -> 7.4 | V10: El pianista (2002) es uno de los grandes retratos sobrios del Holocausto, centrado en la supervivencia. | Y10: tt0253474
A11: Luces de la ciudad | B11: 1931 | C11: 1930s | D11: 87 | E11: Charles Chaplin | F11: 8.5 | H11: 217749 | I11: EE.UU. | J11: Romance | K11: Comedia | L11: Acontra, Acontra Plus Amazon Channel | M11: Chaplin interpreta a un vagabundo enamorado de una florista ciega. | N11: 0 | O11: 0 | P11: 0 | Q11: 0 | R11: 0 | S11: 0 | T11: 36 | U11: =O11*4 + P11*2 + MAX(0,N11-O11-P11)*1 + Q11*0.2 + R11*2 + S11*1 + IF(T11="",0,IF(T11<=10,8,IF(T11<=50,6,IF(T11<=100,4,2)))) -> 6 | V11: Luces de la ciudad (1931) representa la fusión perfecta del slapstick de Chaplin con un profundo componente. | Y11: tt0021749
A12: Gran Torino | B12: 2008 | C12: 2000s | D12: 116 | E12: Clint Eastwood | F12: 8.1 | G12: 8 | H12: 867929 | I12: EE.UU. | J12: Drama | K12: Mafia | L12: Prime, Movistar, Movistar Plus+ Ficción Total , HBO Max, HBO Max Amazon Channel | M12: Un veterano se enfrenta a sus prejuicios y entabla amistad con un joven hmong. | N12: 0 | O12: 0 | P12: 0 | Q12: 0 | R12: 0 | S12: 0 | U12: =O12*4 + P12*2 + MAX(0,N12-O12-P12)*1 + Q12*0.2 + R12*2 + S12*1 + IF(T12="",0,IF(T12<=10,8,IF(T12<=50,6,IF(T12<=100,4,2)))) -> 0 | V12: Gran Torino (2008) es considerada una obra clave del cine de su época, y una pieza importante en la. | Y12: tt1205489
A13: Terminator | B13: 1984 | C13: 1980s | D13: 107 | E13: James Cameron | F13: 8.1 | G13: 7 | H13: 1013987 | I13: EE.UU. | J13: Ciencia ficción | K13: Acción | L13: Prime | M13: Un cyborg asesino llega del futuro para matar a Sarah Connor, cuyo hijo aún no nacido será. | N13: 0 | O13: 0 | P13: 0 | Q13: 0 | R13: 0 | S13: 0 | U13: =O13*4 + P13*2 + MAX(0,N13-O13-P13)*1 + Q13*0.2 + R13*2 + S13*1 + IF(T13="",0,IF(T13<=10,8,IF(T13<=50,6,IF(T13<=100,4,2)))) -> 0 | Y13: tt0088247
A14: El padrino. Parte II | B14: 1974 | C14: 1970s | D14: 202 | E14: Francis F. Coppola | F14: 9 | G14: 10 | H14: 1507335 | I14: EE.UU. | J14: Drama | K14: Crimen | L14: Netflix, Movistar Plus+ Ficción Total , Filmin, SkyShowtime | M14: Michael consolida su poder mientras se cuenta el ascenso de su padre. | N14: 6 | O14: 1 | P14: 1 | Q14: 11 | R14: 0 | S14: 0 | T14: 104 | U14: =O14*4 + P14*2 + MAX(0,N14-O14-P14)*1 + Q14*0.2 + R14*2 + S14*1 + IF(T14="",0,IF(T14<=10,8,IF(T14<=50,6,IF(T14<=100,4,2)))) -> 14.2 | V14: El padrino. | W14: #6 | Y14: tt0071562
A15: Harakiri | B15: 1962 | C15: 1960s | D15: 133 | E15: Masaki Kobayashi | F15: 8.6 | H15: 93309 | I15: Japón | J15: Drama | K15: Misterio | L15: Prime, Filmin, Acontra | M15: Un samurái sin señor pide morir en casa de un clan. | N15: 0 | O15: 0 | P15: 0 | Q15: 0 | R15: 0 | S15: 0 | U15: =O15*4 + P15*2 + MAX(0,N15-O15-P15)*1 + Q15*0.2 + R15*2 + S15*1 + IF(T15="",0,IF(T15<=10,8,IF(T15<=50,6,IF(T15<=100,4,2)))) -> 0 | V15: Harakiri (1962) es considerada una obra clave del género drama, samurai, y una pieza importante en la. | W15: TOP 30-40 | Y15: tt0056058
A16: Reservoir Dogs | B16: 1992 | C16: 1990s | D16: 99 | E16: Quentin Tarantino | F16: 8.2 | G16: 8 | H16: 1178280 | I16: EE.UU. | J16: Thriller | K16: Atracos | L16: Filmin, Lionsgate+ Amazon Channel | M16: Criminales sospechan que uno de ellos es un infiltrado tras un atraco fallido. | N16: 0 | O16: 0 | P16: 0 | Q16: 0 | R16: 0 | S16: 0 | U16: =O16*4 + P16*2 + MAX(0,N16-O16-P16)*1 + Q16*0.2 + R16*2 + S16*1 + IF(T16="",0,IF(T16<=10,8,IF(T16<=50,6,IF(T16<=100,4,2)))) -> 0 | V16: Reservoir Dogs (1992) supuso la irrupción de Tarantino y redefinió el cine independiente de los 90 con su. | Y16: tt0105236
A17: Ciudad de Dios | B17: 2002 | C17: 2000s | D17: 130 | E17: Fernando Meirelles | F17: 8.6 | G17: 10 | H17: 878822 | I17: Brasil | J17: Drama | K17: Crimen | L17: Movistar, Movistar Plus+ Ficción Total , Acontra, Acontra Plus Amazon Channel, Runtime | M17: Dos chavales de una favela: uno fotógrafo, otro narco. | N17: 0 | O17: 0 | P17: 0 | Q17: 4 | R17: 0 | S17: 0 | U17: =O17*4 + P17*2 + MAX(0,N17-O17-P17)*1 + Q17*0.2 + R17*2 + S17*1 + IF(T17="",0,IF(T17<=10,8,IF(T17<=50,6,IF(T17<=100,4,2)))) -> 0.8 | V17: Ciudad de Dios (2002) revolucionó el cine de barrio marginal con un estilo visual eléctrico y montaje. | W17: Casi top | Y17: tt0317248
A18: Psicosis | B18: 1960 | C18: 1960s | D18: 109 | E18: Alfred Hitchcock | F18: 8.5 | G18: 8 | H18: 791672 | I18: EE.UU. | J18: Terror | K18: Misterio | M18: Una joven desaparece tras robar dinero y termina en un motel regentado por Norman Bates. | N18: 0 | O18: 0 | P18: 0 | Q18: 4 | R18: 0 | S18: 0 | T18: 31 | U18: =O18*4 + P18*2 + MAX(0,N18-O18-P18)*1 + Q18*0.2 + R18*2 + S18*1 + IF(T18="",0,IF(T18<=10,8,IF(T18<=50,6,IF(T18<=100,4,2)))) -> 6.8 | V18: Psicosis (1960) es considerada una obra clave del género terror, thriller, y una pieza importante en la. | Y18: tt0054215
A19: La chaqueta metálica | B19: 1987 | C19: 1980s | D19: 116 | E19: Stanley Kubrick | F19: 8.2 | H19: 856754 | I19: EE.UU., Reino Unido | J19: Bélico | K19: Drama | L19: Movistar, Movistar Plus+ Ficción Total , HBO Max, HBO Max Amazon Channel | M19: Reclutas marines viven un entrenamiento brutal antes del combate. | N19: 0 | O19: 0 | P19: 0 | Q19: 1 | R19: 0 | S19: 0 | U19: =O19*4 + P19*2 + MAX(0,N19-O19-P19)*1 + Q19*0.2 + R19*2 + S19*1 + IF(T19="",0,IF(T19<=10,8,IF(T19<=50,6,IF(T19<=100,4,2)))) -> 0.2 | V19: La chaqueta metálica (1987) es considerada una obra clave del cine de su época, y una pieza importante en la. | Y19: tt0093058
A20: Réquiem por un sueño | B20: 2000 | C20: 2000s | D20: 102 | E20: Darren Aronofsky | F20: 8.3 | H20: 981736 | I20: EE.UU. | J20: Drama | L20: Lionsgate+ Amazon Channel | M20: Harry (Jared Leto) y su madre (Ellen Burstyn) tienen sueños muy distintos: ella está. | N20: 0 | O20: 0 | P20: 0 | Q20: 1 | R20: 0 | S20: 0 | U20: =O20*4 + P20*2 + MAX(0,N20-O20-P20)*1 + Q20*0.2 + R20*2 + S20*1 + IF(T20="",0,IF(T20<=10,8,IF(T20<=50,6,IF(T20<=100,4,2)))) -> 0.2 | Y20: tt0180093
A21: Taxi Driver | B21: 1976 | C21: 1970s | D21: 114 | E21: Martin Scorsese | F21: 8.2 | G21: 8 | H21: 1037580 | I21: EE.UU. | J21: Drama | K21: Crimen | L21: Movistar, Movistar Plus+ Ficción Total , Filmin | M21: Un taxista insomne se obsesiona con limpiar Nueva York. | N21: 0 | O21: 0 | P21: 0 | Q21: 4 | R21: 1 | S21: 0 | T21: 29 | U21: =O21*4 + P21*2 + MAX(0,N21-O21-P21)*1 + Q21*0.2 + R21*2 + S21*1 + IF(T21="",0,IF(T21<=10,8,IF(T21<=50,6,IF(T21<=100,4,2)))) -> 8.8 | V21: Cima del Nuevo Hollywood: el antihéroe urbano alienado y la violencia como catarsis, con el Nueva York. | W21: #9 | Y21: tt0075314
A22: Una mente maravillosa | B22: 2001 | C22: 2000s | D22: 135 | E22: Ron Howard | F22: 8.2 | H22: 1060822 | I22: EE.UU. | J22: Drama | K22: Misterio | M22: Obsesionado con la búsqueda de una idea matemática original, el brillante estudiante John. | N22: 4 | O22: 1 | P22: 1 | Q22: 8 | R22: 0 | S22: 1 | U22: =O22*4 + P22*2 + MAX(0,N22-O22-P22)*1 + Q22*0.2 + R22*2 + S22*1 + IF(T22="",0,IF(T22<=10,8,IF(T22<=50,6,IF(T22<=100,4,2)))) -> 10.6 | Y22: tt0268978
A23: Cisne negro | B23: 2010 | C23: 2010s | D23: 108 | E23: Darren Aronofsky | F23: 8 | H23: 895252 | I23: EE.UU. | J23: Thriller | K23: Drama | L23: Disney+ | M23: Nina (Natalie Portman), una brillante bailarina que forma parte de una compañía de ballet de. | N23: 1 | O23: 0 | P23: 0 | Q23: 5 | R23: 0 | S23: 0 | U23: =O23*4 + P23*2 + MAX(0,N23-O23-P23)*1 + Q23*0.2 + R23*2 + S23*1 + IF(T23="",0,IF(T23<=10,8,IF(T23<=50,6,IF(T23<=100,4,2)))) -> 2 | Y23: tt0947798
A24: Uno de los nuestros | B24: 1990 | C24: 1990s | D24: 145 | E24: Martin Scorsese | F24: 8.7 | G24: 8 | H24: 1406721 | I24: EE.UU. | J24: Drama | K24: Crimen | L24: Movistar, Movistar Plus+ Ficción Total , HBO Max, HBO Max Amazon Channel | M24: El ascenso y caída de un gánster de barrio. | N24: 1 | O24: 0 | P24: 0 | Q24: 6 | R24: 0 | S24: 0 | T24: 63 | U24: =O24*4 + P24*2 + MAX(0,N24-O24-P24)*1 + Q24*0.2 + R24*2 + S24*1 + IF(T24="",0,IF(T24<=10,8,IF(T24<=50,6,IF(T24<=100,4,2)))) -> 6.2 | V24: Uno de los nuestros (1990) redefinió el cine de mafia moderno con su voz en off, montaje vertiginoso y uso de. | W24: TOP 20-30 | Y24: tt0099685
A25: El apartamento | B25: 1960 | C25: 1960s | D25: 125 | E25: Billy Wilder | F25: 8.3 | H25: 222306 | I25: EE.UU. | J25: Romance | K25: Comedia | L25: MGM Plus Amazon Channel | M25: Un oficinista presta su piso a los jefes para sus líos. | N25: 5 | O25: 1 | P25: 1 | Q25: 10 | R25: 0 | S25: 1 | T25: 54 | U25: =O25*4 + P25*2 + MAX(0,N25-O25-P25)*1 + Q25*0.2 + R25*2 + S25*1 + IF(T25="",0,IF(T25<=10,8,IF(T25<=50,6,IF(T25<=100,4,2)))) -> 16 | V25: El apartamento (1960) es considerada una obra clave del género comedia, romance, y una pieza importante en la. | W25: TOP 30-40 | Y25: tt0053604
A26: Indiana Jones y el templo maldito | B26: 1984 | C26: 1980s | D26: 118 | E26: Steven Spielberg | F26: 7.5 | H26: 572243 | I26: EE.UU. | J26: Acción | K26: Aventura | L26: Movistar Plus+ Ficción Total , SkyShowtime | M26: 1935. | N26: 1 | O26: 0 | P26: 0 | Q26: 2 | R26: 0 | S26: 0 | U26: =O26*4 + P26*2 + MAX(0,N26-O26-P26)*1 + Q26*0.2 + R26*2 + S26*1 + IF(T26="",0,IF(T26<=10,8,IF(T26<=50,6,IF(T26<=100,4,2)))) -> 1.4 | Y26: tt0087469
A27: Los siete samuráis | B27: 1954 | C27: 1950s | D27: 207 | E27: Akira Kurosawa | F27: 8.6 | G27: 8 | H27: 406042 | I27: Japón | J27: Acción | K27: Drama | L27: Movistar, Movistar Plus+ Ficción Total , Filmin, Acontra, Acontra Plus Amazon Channel, Tivify, Runtime | M27: Unos aldeanos contratan samuráis para defenderse de bandidos. | N27: 0 | O27: 0 | P27: 0 | Q27: 2 | R27: 0 | S27: 0 | T27: 20 | U27: =O27*4 + P27*2 + MAX(0,N27-O27-P27)*1 + Q27*0.2 + R27*2 + S27*1 + IF(T27="",0,IF(T27<=10,8,IF(T27<=50,6,IF(T27<=100,4,2)))) -> 6.4 | V27: Los siete samuráis (1954) es pilar del cine de aventuras y acción en grupo; su estructura ha sido imitada en. | W27: TOP 10-20 | Y27: tt0047478
A28: Alguien voló sobre el nido del cuco | B28: 1975 | C28: 1970s | D28: 133 | E28: Milos Forman | F28: 8.6 | G28: 7 | H28: 1163711 | I28: EE.UU. | J28: Drama | L28: Filmin | M28: Un rebelde preso es enviado a un hospital psiquiátrico dominado por una enfermera tiránica. | N28: 5 | O28: 1 | P28: 1 | Q28: 9 | R28: 0 | S28: 1 | U28: =O28*4 + P28*2 + MAX(0,N28-O28-P28)*1 + Q28*0.2 + R28*2 + S28*1 + IF(T28="",0,IF(T28<=10,8,IF(T28<=50,6,IF(T28<=100,4,2)))) -> 11.8 | V28: Alguien voló sobre el nido del cuco (1975) es símbolo de la rebelión contra las instituciones opresivas y. | Y28: tt0073486
A29: La milla verde | B29: 1999 | C29: 1990s | D29: 189 | E29: Frank Darabont | F29: 8.6 | H29: 1578084 | I29: EE.UU. | J29: Fantasía | K29: Crimen | L29: Movistar, Movistar Plus+ Ficción Total | M29: Un guardia de prisiones descubre que un condenado a muerte posee un don sobrenatural capaz de. | N29: 0 | O29: 0 | P29: 0 | Q29: 4 | R29: 0 | S29: 0 | U29: =O29*4 + P29*2 + MAX(0,N29-O29-P29)*1 + Q29*0.2 + R29*2 + S29*1 + IF(T29="",0,IF(T29<=10,8,IF(T29<=50,6,IF(T29<=100,4,2)))) -> 0.8 | Y29: tt0120689
A30: Apocalypse Now | B30: 1979 | C30: 1970s | D30: 147 | E30: Francis F. Coppola | F30: 8.4 | H30: 775671 | I30: EE.UU. | J30: Bélico | K30: Misterio | L30: Filmin | M30: Un capitán remonta el río para eliminar a un coronel renegado. | N30: 2 | O30: 0 | P30: 0 | Q30: 8 | R30: 1 | S30: 0 | T30: 19 | U30: =O30*4 + P30*2 + MAX(0,N30-O30-P30)*1 + Q30*0.2 + R30*2 + S30*1 + IF(T30="",0,IF(T30<=10,8,IF(T30<=50,6,IF(T30<=100,4,2)))) -> 11.6 | V30: Apocalypse Now (1979) es considerada una obra clave del género bélico, drama, y una pieza importante en la. | W30: TOP 10-20 | Y30: tt0078788
A31: La evasión | B31: 1960 | C31: 1960s | D31: 131 | E31: Jacques Becker | F31: 8.5 | H31: 24017 | I31: Francia | J31: Thriller | K31: Crimen | L31: Tivify | M31: Un preso político trama una fuga minuciosa durante la Segunda Guerra Mundial. | N31: 0 | O31: 0 | P31: 0 | Q31: 0 | R31: 0 | S31: 0 | U31: =O31*4 + P31*2 + MAX(0,N31-O31-P31)*1 + Q31*0.2 + R31*2 + S31*1 + IF(T31="",0,IF(T31<=10,8,IF(T31<=50,6,IF(T31<=100,4,2)))) -> 0 | V31: La evasión (1960) es considerada una obra clave del género crimen, thriller, prisión, y una pieza importante. | Y31: tt0054407
A32: Seven | B32: 1995 | C32: 1990s | D32: 127 | E32: David Fincher | F32: 8.6 | G32: 9 | H32: 2048370 | I32: EE.UU. | J32: Drama | K32: Crimen | L32: Prime, Movistar Plus+ Ficción Total | M32: Dos detectives persiguen a un asesino serial que usa los siete pecados capitales. | N32: 0 | O32: 0 | P32: 0 | Q32: 1 | R32: 0 | S32: 0 | U32: =O32*4 + P32*2 + MAX(0,N32-O32-P32)*1 + Q32*0.2 + R32*2 + S32*1 + IF(T32="",0,IF(T32<=10,8,IF(T32<=50,6,IF(T32<=100,4,2)))) -> 0.2 | V32: Seven (1995) redefinió el thriller oscuro contemporáneo, con un final impactante y una atmósfera opresiva muy. | Y32: tt0114369
A33: Mar adentro | B33: 2004 | C33: 2000s | D33: 126 | E33: Alejandro Amenábar | F33: 7.9 | H33: 89284 | I33: España | J33: Drama | K33: Biográfico | L33: Netflix, Movistar Plus+ Ficción Total , FlixOlé, HBO Max, FlixOlé Amazon Channel, HBO Max Amazon Channel | M33: Ramón (Javier Bardem) lleva casi treinta años postrado en una cama al cuidado de su familia. | N33: 1 | O33: 0 | P33: 0 | Q33: 2 | R33: 0 | S33: 0 | U33: =O33*4 + P33*2 + MAX(0,N33-O33-P33)*1 + Q33*0.2 + R33*2 + S33*1 + IF(T33="",0,IF(T33<=10,8,IF(T33<=50,6,IF(T33<=100,4,2)))) -> 1.4 | Y33: tt0369702
A34: El golpe | B34: 1973 | C34: 1970s | D34: 129 | E34: George Roy Hill | F34: 8.2 | H34: 304623 | I34: EE.UU. | J34: Comedia | K34: Crimen | L34: Netflix | M34: Dos estafadores planean un gran golpe en los años 30. | N34: 7 | O34: 1 | P34: 1 | Q34: 10 | R34: 0 | S34: 0 | U34: =O34*4 + P34*2 + MAX(0,N34-O34-P34)*1 + Q34*0.2 + R34*2 + S34*1 + IF(T34="",0,IF(T34<=10,8,IF(T34<=50,6,IF(T34<=100,4,2)))) -> 13 | V34: El golpe (1973) consolidó el cine de estafas como gran espectáculo popular, con un guion modélico lleno de. | Y34: tt0070735
A35: Casablanca | B35: 1942 | C35: 1940s | D35: 102 | E35: Michael Curtiz | F35: 8.5 | H35: 659159 | I35: EE.UU. | J35: Bélico | K35: Espionaje | M35: Un hombre debe elegir entre su amor y ayudar a la resistencia durante la Segunda Guerra. | N35: 3 | O35: 1 | P35: 1 | Q35: 8 | R35: 0 | S35: 0 | T35: 63 | U35: =O35*4 + P35*2 + MAX(0,N35-O35-P35)*1 + Q35*0.2 + R35*2 + S35*1 + IF(T35="",0,IF(T35<=10,8,IF(T35<=50,6,IF(T35<=100,4,2)))) -> 12.6 | V35: Casablanca (1942) es un melodrama romántico icónico, estudiado por su guion, diálogos y uso del contexto. | Y35: tt0034583
A36: Cinema Paradiso | B36: 1988 | C36: 1980s | D36: 174 | E36: Giuseppe Tornatore | F36: 8.5 | H36: 319465 | I36: Italia | J36: Romance | K36: Coming of age | L36: Prime, Acontra | M36: Un cineasta recuerda su infancia marcada por su amistad con el proyeccionista del cine local. | N36: 1 | O36: 0 | P36: 0 | Q36: 1 | R36: 0 | S36: 0 | U36: =O36*4 + P36*2 + MAX(0,N36-O36-P36)*1 + Q36*0.2 + R36*2 + S36*1 + IF(T36="",0,IF(T36<=10,8,IF(T36<=50,6,IF(T36<=100,4,2)))) -> 1.2 | V36: Cinema Paradiso (1988) es quizá la carta de amor al cine más famosa, consolidando la idea del cine como. | Y36: tt0095765
A37: La historia interminable | B37: 1984 | C37: 1980s | D37: 102 | E37: Wolfgang Petersen | F37: 7.3 | H37: 171979 | I37: Alemania | J37: Aventura | K37: Familiar | L37: Lionsgate+ Amazon Channel, Rakuten | M37: Un niño viaja a un mundo mágico para salvar a la Emperatriz Infantil y detener la Nada que. | N37: 0 | O37: 0 | P37: 0 | Q37: 0 | R37: 0 | S37: 0 | U37: =O37*4 + P37*2 + MAX(0,N37-O37-P37)*1 + Q37*0.2 + R37*2 + S37*1 + IF(T37="",0,IF(T37<=10,8,IF(T37<=50,6,IF(T37<=100,4,2)))) -> 0 | Y37: tt0088323
A38: Con faldas y a lo loco | B38: 1959 | C38: 1950s | D38: 121 | E38: Billy Wilder | F38: 8.2 | H38: 306558 | I38: EE.UU. | J38: Musical | K38: Romance | L38: MGM Plus Amazon Channel | M38: Dos músicos huyen disfrazados de mujer tras presenciar un crimen. | N38: 1 | O38: 0 | P38: 0 | Q38: 6 | R38: 0 | S38: 1 | T38: 38 | U38: =O38*4 + P38*2 + MAX(0,N38-O38-P38)*1 + Q38*0.2 + R38*2 + S38*1 + IF(T38="",0,IF(T38<=10,8,IF(T38<=50,6,IF(T38<=100,4,2)))) -> 9.2 | V38: Con faldas y a lo loco (1959) es considerada una obra clave del género comedia, y una pieza importante en la. | Y38: tt0053291
A39: Sin perdón | B39: 1992 | C39: 1990s | D39: 130 | E39: Clint Eastwood | F39: 8.2 | G39: 8 | H39: 471361 | I39: EE.UU. | J39: Western | K39: Drama | L39: Movistar, Movistar Plus+ Ficción Total | M39: Un pistolero retirado acepta un último encargo. | N39: 4 | O39: 1 | P39: 1 | Q39: 9 | R39: 0 | S39: 0 | U39: =O39*4 + P39*2 + MAX(0,N39-O39-P39)*1 + Q39*0.2 + R39*2 + S39*1 + IF(T39="",0,IF(T39<=10,8,IF(T39<=50,6,IF(T39<=100,4,2)))) -> 9.8 | V39: Sin perdón (1992) es considerada una obra clave del género western, drama, y una pieza importante en la. | W39: TOP 30-40 | Y39: tt0105695
A40: El precio del poder | B40: 1983 | C40: 1980s | D40: 170 | E40: Brian De Palma | F40: 8.3 | G40: 9 | H40: 1029271 | I40: EE.UU. | J40: Drama | K40: Crimen | L40: Netflix, rtve | M40: Tony Montana asciende en el narcotráfico hasta caer víctima de su ambición. | N40: 0 | O40: 0 | P40: 0 | Q40: 0 | R40: 0 | S40: 0 | U40: =O40*4 + P40*2 + MAX(0,N40-O40-P40)*1 + Q40*0.2 + R40*2 + S40*1 + IF(T40="",0,IF(T40<=10,8,IF(T40<=50,6,IF(T40<=100,4,2)))) -> 0 | V40: El precio del poder (1983) es considerada una obra clave del género crimen, y una pieza importante en la. | Y40: tt0086250
A41: El discurso del Rey | B41: 2010 | C41: 2010s | D41: 118 | E41: Tom Hooper | F41: 8 | H41: 735659 | I41: Reino Unido | J41: Drama | K41: Biográfico | L41: Netflix, Prime, Disney+, Movistar, Movistar Plus+ Ficción Total | M41: El duque de York se convirtió en rey de Inglaterra con el nombre de Jorge VI (1936-1952), tras. | N41: 4 | O41: 1 | P41: 1 | Q41: 12 | R41: 0 | S41: 0 | U41: =O41*4 + P41*2 + MAX(0,N41-O41-P41)*1 + Q41*0.2 + R41*2 + S41*1 + IF(T41="",0,IF(T41<=10,8,IF(T41<=50,6,IF(T41<=100,4,2)))) -> 10.4 | Y41: tt1504320
A42: El hombre que mató a Liberty Valance | B42: 1962 | C42: 1960s | D42: 123 | E42: John Ford | F42: 8.1 | H42: 89465 | I42: EE.UU. | J42: Western | K42: Drama | M42: Un abogado se hace famoso por matar a un pistolero. | N42: 0 | O42: 0 | P42: 0 | Q42: 1 | R42: 0 | S42: 0 | T42: 108 | U42: =O42*4 + P42*2 + MAX(0,N42-O42-P42)*1 + Q42*0.2 + R42*2 + S42*1 + IF(T42="",0,IF(T42<=10,8,IF(T42<=50,6,IF(T42<=100,4,2)))) -> 2.2 | V42: El hombre que mató a Liberty Valance (1962) es considerada una obra clave del género western, y una pieza. | W42: #3 | Y42: tt0056217
A43: El secreto de sus ojos | B43: 2009 | C43: 2000s | D43: 129 | E43: Juan José Campanella | F43: 8.2 | H43: 244491 | I43: Argentina | J43: Romance | K43: Misterio | L43: Netflix, Movistar, Movistar Plus+ Ficción Total , FlixOlé, HBO Max, HBO Max Amazon Channel | M43: Benjamín Espósito es oficial de un Juzgado de Instrucción de Buenos Aires recién retirado. | N43: 1 | O43: 0 | P43: 0 | Q43: 1 | R43: 0 | S43: 0 | U43: =O43*4 + P43*2 + MAX(0,N43-O43-P43)*1 + Q43*0.2 + R43*2 + S43*1 + IF(T43="",0,IF(T43<=10,8,IF(T43<=50,6,IF(T43<=100,4,2)))) -> 1.2 | Y43: tt1305806
A44: Bailando con lobos | B44: 1990 | C44: 1990s | D44: 181 | E44: Kevin Costner | F44: 8 | H44: 312300 | I44: EE.UU. | J44: Western | K44: Aventura | L44: Prime | M44: Tras la Guerra de Secesión (1861-1865) y en plena colonización del Oeste (1785-1890), el. | N44: 7 | O44: 1 | P44: 1 | Q44: 12 | R44: 0 | S44: 1 | U44: =O44*4 + P44*2 + MAX(0,N44-O44-P44)*1 + Q44*0.2 + R44*2 + S44*1 + IF(T44="",0,IF(T44<=10,8,IF(T44<=50,6,IF(T44<=100,4,2)))) -> 14.4 | Y44: tt0099348
A45: Babel | B45: 2006 | C45: 2000s | D45: 143 | E45: Alejandro González Iñárritu | F45: 7.4 | H45: 330446 | I45: EE.UU. | J45: Drama | M45: Ambientada en Marruecos, Túnez, México y Japón. | N45: 1 | O45: 0 | P45: 0 | Q45: 7 | R45: 0 | S45: 1 | U45: =O45*4 + P45*2 + MAX(0,N45-O45-P45)*1 + Q45*0.2 + R45*2 + S45*1 + IF(T45="",0,IF(T45<=10,8,IF(T45<=50,6,IF(T45<=100,4,2)))) -> 3.4 | Y45: tt0449467
A46: El gran dictador | B46: 1940 | C46: 1940s | D46: 125 | E46: Charles Chaplin | F46: 8.4 | H46: 259744 | I46: EE.UU. | J46: Bélico | K46: Comedia | L46: Acontra, Acontra Plus Amazon Channel, Tivify, Runtime | M46: Chaplin satiriza a Hitler y los regímenes totalitarios. | N46: 0 | O46: 0 | P46: 0 | Q46: 5 | R46: 0 | S46: 0 | U46: =O46*4 + P46*2 + MAX(0,N46-O46-P46)*1 + Q46*0.2 + R46*2 + S46*1 + IF(T46="",0,IF(T46<=10,8,IF(T46<=50,6,IF(T46<=100,4,2)))) -> 1 | V46: El gran dictador (1940) es una sátira temprana y valiente contra Hitler y el fascismo, esencial para entender. | Y46: tt0032553
A47: Los chicos del coro | B47: 2004 | C47: 2000s | D47: 97 | E47: Christophe Barratier | F47: 7.9 | H47: 72607 | I47: Francia | J47: Musical | K47: Drama | L47: Prime, Disney+, Movistar Plus+ Ficción Total , FlixOlé, FlixOlé Amazon Channel, Tivify, AMC Channels Amazon Channel | M47: En 1948 Clément Mathieu, profesor de música desempleado, acepta un puesto como profesor. | N47: 0 | O47: 0 | P47: 0 | Q47: 2 | R47: 0 | S47: 0 | U47: =O47*4 + P47*2 + MAX(0,N47-O47-P47)*1 + Q47*0.2 + R47*2 + S47*1 + IF(T47="",0,IF(T47<=10,8,IF(T47<=50,6,IF(T47<=100,4,2)))) -> 0.4 | Y47: tt0372824
A48: M, el vampiro de Düsseldorf | B48: 1931 | C48: 1930s | D48: 99 | E48: Fritz Lang | F48: 8.3 | H48: 183925 | I48: Alemania | J48: Thriller | K48: Crimen | L48: Prime, Filmin, Plex | M48: Un asesino de niñas aterroriza Berlín mientras criminales y policía lo persiguen. | N48: 0 | O48: 0 | P48: 0 | Q48: 0 | R48: 0 | S48: 0 | T48: 36 | U48: =O48*4 + P48*2 + MAX(0,N48-O48-P48)*1 + Q48*0.2 + R48*2 + S48*1 + IF(T48="",0,IF(T48<=10,8,IF(T48<=50,6,IF(T48<=100,4,2)))) -> 6 | V48: M, el vampiro de Düsseldorf (1931) es considerada una obra clave del género thriller, y una pieza importante. | Y48: tt0022100
A49: En el nombre del padre | B49: 1993 | C49: 1990s | D49: 133 | E49: Jim Sheridan | F49: 8.1 | G49: 8 | H49: 204157 | I49: Reino Unido, Irlanda | J49: Drama | K49: Crimen | M49: Un hombre condenado injustamente lucha por demostrar su inocencia. | N49: 0 | O49: 0 | P49: 0 | Q49: 7 | R49: 1 | S49: 0 | U49: =O49*4 + P49*2 + MAX(0,N49-O49-P49)*1 + Q49*0.2 + R49*2 + S49*1 + IF(T49="",0,IF(T49<=10,8,IF(T49<=50,6,IF(T49<=100,4,2)))) -> 3.4 | V49: En el nombre del padre (1993) es considerada una obra clave del cine de su época, y una pieza importante en. | Y49: tt0107207
A50: Forrest Gump | B50: 1994 | C50: 1990s | D50: 142 | E50: Robert Zemeckis | F50: 8.8 | G50: 9 | H50: 2523836 | I50: EE.UU. | J50: Romance | K50: Vietnam | M50: Un hombre bondadoso vive eventos históricos clave mientras busca a su amor de infancia. | N50: 6 | O50: 1 | P50: 1 | Q50: 13 | R50: 0 | S50: 1 | U50: =O50*4 + P50*2 + MAX(0,N50-O50-P50)*1 + Q50*0.2 + R50*2 + S50*1 + IF(T50="",0,IF(T50<=10,8,IF(T50<=50,6,IF(T50<=100,4,2)))) -> 13.6 | V50: Forrest Gump (1994) es un fenómeno cultural que mezcla melodrama y recorrido histórico, muy influyente en el. | Y50: tt0109830
A51: Ciudadano Kane | B51: 1941 | C51: 1940s | D51: 119 | E51: Orson Welles | F51: 8.2 | H51: 495533 | I51: EE.UU. | J51: Drama | K51: Misterio | L51: Prime, Movistar, Movistar Plus+ Ficción Total , FlixOlé | M51: Un periodista investiga la última palabra de un magnate. | N51: 1 | O51: 0 | P51: 0 | Q51: 9 | R51: 0 | S51: 1 | T51: 3 | U51: =O51*4 + P51*2 + MAX(0,N51-O51-P51)*1 + Q51*0.2 + R51*2 + S51*1 + IF(T51="",0,IF(T51<=10,8,IF(T51<=50,6,IF(T51<=100,4,2)))) -> 11.8 | V51: Ciudadano Kane (1941) es quizá la película más analizada de la historia del cine por sus innovaciones. | W51: #5 | Y51: tt0033467
A52: El silencio de los corderos | B52: 1991 | C52: 1990s | D52: 118 | E52: Jonathan Demme | F52: 8.6 | G52: 8 | H52: 1741359 | I52: EE.UU. | J52: Terror | K52: Crimen | L52: Prime | M52: Una agente del FBI consulta a Hannibal Lecter para capturar a un asesino serial. | N52: 5 | O52: 1 | P52: 1 | Q52: 7 | R52: 0 | S52: 0 | U52: =O52*4 + P52*2 + MAX(0,N52-O52-P52)*1 + Q52*0.2 + R52*2 + S52*1 + IF(T52="",0,IF(T52<=10,8,IF(T52<=50,6,IF(T52<=100,4,2)))) -> 10.4 | V52: El silencio de los corderos (1991) consolidó el thriller psicológico de asesinos en serie y creó una figura. | Y52: tt0102926
A53: La naranja mecánica | B53: 1971 | C53: 1970s | D53: 136 | E53: Stanley Kubrick | F53: 8.2 | G53: 8 | H53: 942177 | I53: Reino Unido | J53: Ciencia ficción | K53: Crimen | M53: Un joven ultra violento se somete a una terapia experimental. | N53: 0 | O53: 0 | P53: 0 | Q53: 4 | R53: 0 | S53: 0 | T53: 243 | U53: =O53*4 + P53*2 + MAX(0,N53-O53-P53)*1 + Q53*0.2 + R53*2 + S53*1 + IF(T53="",0,IF(T53<=10,8,IF(T53<=50,6,IF(T53<=100,4,2)))) -> 2.8 | V53: La naranja mecánica (1971) es una de las obras más polémicas de Kubrick y referencia del cine distópico sobre. | Y53: tt0066921
A54: Todo sobre mi madre | B54: 1999 | C54: 1990s | D54: 101 | E54: Pedro Almodóvar | F54: 7.8 | H54: 110415 | I54: España | J54: Romance | K54: Comedia | L54: Netflix, Movistar, Movistar Plus+ Ficción Total , rtve | M54: Tras la muerte de su hijo, una madre viaja a Barcelona en busca del padre del chico. | N54: 1 | O54: 0 | P54: 0 | Q54: 1 | R54: 0 | S54: 0 | T54: 157 | U54: =O54*4 + P54*2 + MAX(0,N54-O54-P54)*1 + Q54*0.2 + R54*2 + S54*1 + IF(T54="",0,IF(T54<=10,8,IF(T54<=50,6,IF(T54<=100,4,2)))) -> 3.2 | V54: Consagró a Almodóvar y ganó el Óscar a mejor película extranjera. | Y54: tt0185125
A55: Good bye, Lenin! | B55: 2003 | C55: 2000s | D55: 121 | E55: Wolfgang Becker | F55: 7.7 | H55: 160564 | I55: Alemania | J55: Romance | K55: Comedia | L55: Prime, Acontra | M55: Berlín, octubre de 1989. | N55: 0 | O55: 0 | P55: 0 | Q55: 0 | R55: 0 | S55: 0 | U55: =O55*4 + P55*2 + MAX(0,N55-O55-P55)*1 + Q55*0.2 + R55*2 + S55*1 + IF(T55="",0,IF(T55<=10,8,IF(T55<=50,6,IF(T55<=100,4,2)))) -> 0 | Y55: tt0301357
A56: El resplandor | B56: 1980 | C56: 1980s | D56: 146 | E56: Stanley Kubrick | F56: 8.4 | G56: 8 | H56: 1238405 | I56: Reino Unido, EE.UU. | J56: Terror | K56: Drama | L56: Movistar, Movistar Plus+ Ficción Total , HBO Max, HBO Max Amazon Channel | M56: Un escritor se enfrenta a fuerzas malignas en un hotel aislado. | N56: 0 | O56: 0 | P56: 0 | Q56: 0 | R56: 0 | S56: 0 | T56: 88 | U56: =O56*4 + P56*2 + MAX(0,N56-O56-P56)*1 + Q56*0.2 + R56*2 + S56*1 + IF(T56="",0,IF(T56<=10,8,IF(T56<=50,6,IF(T56<=100,4,2)))) -> 4 | V56: El resplandor (1980) es un pilar del terror moderno, con imágenes icónicas y una ambigüedad interpretativa. | Y56: tt0081505
A57: La vida de los otros | B57: 2006 | C57: 2000s | D57: 137 | E57: Florian Henckel von Donnersmarck | F57: 8.4 | H57: 445924 | I57: Alemania | J57: Thriller | K57: Misterio | M57: República Democrática Alemana, año 1984. | N57: 1 | O57: 0 | P57: 0 | Q57: 1 | R57: 0 | S57: 0 | U57: =O57*4 + P57*2 + MAX(0,N57-O57-P57)*1 + Q57*0.2 + R57*2 + S57*1 + IF(T57="",0,IF(T57<=10,8,IF(T57<=50,6,IF(T57<=100,4,2)))) -> 1.2 | Y57: tt0405094
A58: Nueve reinas | B58: 2000 | C58: 2000s | D58: 114 | E58: Fabián Bielinsky | F58: 7.9 | H58: 63470 | I58: Argentina | J58: Thriller | K58: Crimen | L58: Netflix, Prime, Movistar, Movistar Plus+ Ficción Total , Acontra | M58: Buenos Aires. | N58: 0 | O58: 0 | P58: 0 | Q58: 0 | R58: 0 | S58: 0 | U58: =O58*4 + P58*2 + MAX(0,N58-O58-P58)*1 + Q58*0.2 + R58*2 + S58*1 + IF(T58="",0,IF(T58<=10,8,IF(T58<=50,6,IF(T58<=100,4,2)))) -> 0 | Y58: tt0247586
A59: Amores perros | B59: 2000 | C59: 2000s | D59: 154 | E59: Alejandro González Iñárritu | F59: 8 | H59: 272431 | I59: México | J59: Thriller | K59: Drama | L59: MUBI, MUBI Amazon Channel | M59: En Ciudad de México, un fatal accidente automovilístico afecta trágicamente a tres personas. | N59: 0 | O59: 0 | P59: 0 | Q59: 1 | R59: 0 | S59: 0 | U59: =O59*4 + P59*2 + MAX(0,N59-O59-P59)*1 + Q59*0.2 + R59*2 + S59*1 + IF(T59="",0,IF(T59<=10,8,IF(T59<=50,6,IF(T59<=100,4,2)))) -> 0.2 | Y59: tt0245712
A60: As bestas | B60: 2022 | C60: 2020s | D60: 137 | E60: Rodrigo Sorogoyen | F60: 7.5 | G60: 8 | H60: 26251 | I60: España | J60: Thriller | K60: Drama | L60: rtve | M60: Antoine y Olga son una pareja francesa que se instaló hace tiempo en una aldea del interior de. | N60: 0 | O60: 0 | P60: 0 | Q60: 0 | R60: 0 | S60: 0 | U60: =O60*4 + P60*2 + MAX(0,N60-O60-P60)*1 + Q60*0.2 + R60*2 + S60*1 + IF(T60="",0,IF(T60<=10,8,IF(T60<=50,6,IF(T60<=100,4,2)))) -> 0 | Y60: tt15006566
A61: Los Goonies | B61: 1985 | C61: 1980s | D61: 114 | E61: Richard Donner | F61: 7.7 | H61: 329357 | I61: EE.UU. | J61: Aventura | K61: Familiar | L61: Movistar, Movistar Plus+ Ficción Total | M61: Un grupo de niños encuentra un mapa del tesoro y emprende una aventura llena de trampas. | N61: 0 | O61: 0 | P61: 0 | Q61: 0 | R61: 0 | S61: 0 | U61: =O61*4 + P61*2 + MAX(0,N61-O61-P61)*1 + Q61*0.2 + R61*2 + S61*1 + IF(T61="",0,IF(T61<=10,8,IF(T61<=50,6,IF(T61<=100,4,2)))) -> 0 | Y61: tt0089218
A62: Annie Hall | B62: 1977 | C62: 1970s | D62: 93 | E62: Woody Allen | F62: 7.9 | H62: 292384 | I62: EE.UU. | J62: Romance | K62: Musical | L62: MGM Plus Amazon Channel | M62: Un humorista revisa su relación con Annie Hall, explorando neurosis, inseguridades y la. | N62: 4 | O62: 1 | P62: 1 | Q62: 5 | R62: 0 | S62: 0 | T62: 243 | U62: =O62*4 + P62*2 + MAX(0,N62-O62-P62)*1 + Q62*0.2 + R62*2 + S62*1 + IF(T62="",0,IF(T62<=10,8,IF(T62<=50,6,IF(T62<=100,4,2)))) -> 11 | V62: Cambió la comedia romántica y ganó el Óscar a mejor película. | Y62: tt0075686
A63: La ventana indiscreta | B63: 1954 | C63: 1950s | D63: 112 | E63: Alfred Hitchcock | F63: 8.4 | H63: 572257 | I63: EE.UU. | J63: Thriller | K63: Misterio | L63: Movistar Plus+ Ficción Total , SkyShowtime | M63: Un fotógrafo escayolado cree ver un crimen desde su ventana. | N63: 0 | O63: 0 | P63: 0 | Q63: 4 | R63: 0 | S63: 0 | T63: 38 | U63: =O63*4 + P63*2 + MAX(0,N63-O63-P63)*1 + Q63*0.2 + R63*2 + S63*1 + IF(T63="",0,IF(T63<=10,8,IF(T63<=50,6,IF(T63<=100,4,2)))) -> 6.8 | V63: La ventana indiscreta (1954) es considerada una obra clave del género thriller, y una pieza importante en la. | W63: TOP 20-30 | Y63: tt0047396
A64: Vértigo (De entre los muertos) | B64: 1958 | C64: 1950s | D64: 128 | E64: Alfred Hitchcock | F64: 8.2 | H64: 461459 | I64: EE.UU. | J64: Thriller | K64: Misterio | M64: Un detective con vértigo se obsesiona con la mujer que vigila. | N64: 0 | O64: 0 | P64: 0 | Q64: 2 | R64: 0 | S64: 0 | T64: 2 | U64: =O64*4 + P64*2 + MAX(0,N64-O64-P64)*1 + Q64*0.2 + R64*2 + S64*1 + IF(T64="",0,IF(T64<=10,8,IF(T64<=50,6,IF(T64<=100,4,2)))) -> 8.4 | V64: Vértigo (1958) ha pasado a encabezar listas de mejores películas de la historia, clave en el estudio de la. | W64: #2 | Y64: tt0052357
A65: Con la muerte en los talones | B65: 1959 | C65: 1950s | D65: 136 | E65: Alfred Hitchcock | F65: 8.3 | H65: 370753 | I65: EE.UU. | J65: Aventura | K65: Misterio | M65: Un ejecutivo es confundido con un agente del gobierno y perseguido por una organización. | N65: 0 | O65: 0 | P65: 0 | Q65: 3 | R65: 0 | S65: 0 | T65: 45 | U65: =O65*4 + P65*2 + MAX(0,N65-O65-P65)*1 + Q65*0.2 + R65*2 + S65*1 + IF(T65="",0,IF(T65<=10,8,IF(T65<=50,6,IF(T65<=100,4,2)))) -> 6.6 | V65: Con la muerte en los talones (1959) es considerada una obra clave del género thriller, suspense, espionaje, y. | Y65: tt0053125
A66: Abre los ojos | B66: 1997 | C66: 1990s | D66: 119 | E66: Alejandro Amenábar | F66: 7.7 | H66: 76252 | I66: España | J66: Ciencia ficción | K66: Misterio | L66: Netflix, Disney+, Movistar, Movistar Plus+ Ficción Total , FlixOlé, HBO Max, FlixOlé Amazon Channel, HBO Max Amazon Channel | M66: César, un joven acomodado, vive una historia de amor que se transforma en pesadilla tras un. | N66: 0 | O66: 0 | P66: 0 | Q66: 0 | R66: 0 | S66: 0 | U66: =O66*4 + P66*2 + MAX(0,N66-O66-P66)*1 + Q66*0.2 + R66*2 + S66*1 + IF(T66="",0,IF(T66<=10,8,IF(T66<=50,6,IF(T66<=100,4,2)))) -> 0 | Y66: tt0125659
A67: Doce hombres sin piedad | B67: 1957 | C67: 1950s | D67: 96 | E67: Sidney Lumet | F67: 9 | H67: 997731 | I67: EE.UU. | J67: Drama | K67: Crimen | L67: MGM Plus Amazon Channel | M67: Doce jurados deliberan sobre un caso de asesinato, enfrentando prejuicios y dudas. | N67: 0 | O67: 0 | P67: 0 | Q67: 3 | R67: 1 | S67: 0 | U67: =O67*4 + P67*2 + MAX(0,N67-O67-P67)*1 + Q67*0.2 + R67*2 + S67*1 + IF(T67="",0,IF(T67<=10,8,IF(T67<=50,6,IF(T67<=100,4,2)))) -> 2.6 | V67: Doce hombres sin piedad (1957) es el drama judicial por excelencia, ejemplo paradigmático de cómo sacar. | Y67: tt0050083
A68: Desafío total | B68: 1990 | C68: 1990s | D68: 113 | E68: Paul Verhoeven | F68: 7.5 | H68: 383900 | I68: EE.UU. | J68: Ciencia ficción | K68: Acción | L68: Prime, Filmin | M68: Un hombre descubre que sus recuerdos podrían ser implantados y se ve envuelto en una. | N68: 1 | O68: 0 | P68: 0 | Q68: 3 | R68: 0 | S68: 0 | U68: =O68*4 + P68*2 + MAX(0,N68-O68-P68)*1 + Q68*0.2 + R68*2 + S68*1 + IF(T68="",0,IF(T68<=10,8,IF(T68<=50,6,IF(T68<=100,4,2)))) -> 1.6 | Y68: tt0100802
A69: Billy Elliot | B69: 2000 | C69: 2000s | D69: 110 | E69: Stephen Daldry | F69: 7.7 | H69: 153278 | I69: Reino Unido | J69: Musical | K69: Drama | L69: Prime, Movistar Plus+ Ficción Total , Filmin, FlixOlé, FlixOlé Amazon Channel | M69: En 1984, durante una huelga de mineros en el condado de Durham, se suceden los enfrentamientos. | N69: 0 | O69: 0 | P69: 0 | Q69: 3 | R69: 0 | S69: 0 | U69: =O69*4 + P69*2 + MAX(0,N69-O69-P69)*1 + Q69*0.2 + R69*2 + S69*1 + IF(T69="",0,IF(T69<=10,8,IF(T69<=50,6,IF(T69<=100,4,2)))) -> 0.6 | Y69: tt0249462
A70: El paciente inglés | B70: 1996 | C70: 1990s | D70: 162 | E70: Anthony Minghella | F70: 7.4 | H70: 214795 | I70: Reino Unido | J70: Bélico | K70: Romance | L70: Netflix | M70: Durante la Segunda Guerra Mundial, una mujer cuida a un misterioso hombre gravemente herido. | N70: 9 | O70: 1 | P70: 1 | Q70: 12 | R70: 0 | S70: 1 | U70: =O70*4 + P70*2 + MAX(0,N70-O70-P70)*1 + Q70*0.2 + R70*2 + S70*1 + IF(T70="",0,IF(T70<=10,8,IF(T70<=50,6,IF(T70<=100,4,2)))) -> 16.4 | Y70: tt0116209
A71: Memories of Murder | B71: 2003 | C71: 2000s | D71: 131 | E71: Bong Joon-ho | F71: 8.1 | G71: 6 | H71: 272827 | I71: Corea del Sur | J71: Drama | K71: Crimen | L71: Prime, rtve | M71: Dos policías rurales investigan asesinatos en serie. | N71: 0 | O71: 0 | P71: 0 | Q71: 0 | R71: 0 | S71: 0 | U71: =O71*4 + P71*2 + MAX(0,N71-O71-P71)*1 + Q71*0.2 + R71*2 + S71*1 + IF(T71="",0,IF(T71<=10,8,IF(T71<=50,6,IF(T71<=100,4,2)))) -> 0 | V71: Consolidó el thriller coreano y lanzó a Bong Joon-ho. | X71: 106 | Y71: tt0353969
A72: Dogville | B72: 2003 | C72: 2000s | D72: 171 | E72: Lars von Trier | F72: 8 | H72: 168513 | I72: Dinamarca | J72: Drama | K72: Crimen | M72: Grace llega al remoto pueblo de Dogville huyendo de una banda de gángsters. | N72: 0 | O72: 0 | P72: 0 | Q72: 0 | R72: 0 | S72: 0 | U72: =O72*4 + P72*2 + MAX(0,N72-O72-P72)*1 + Q72*0.2 + R72*2 + S72*1 + IF(T72="",0,IF(T72<=10,8,IF(T72<=50,6,IF(T72<=100,4,2)))) -> 0 | Y72: tt0276919
A73: Crimen perfecto | B73: 1954 | C73: 1950s | D73: 105 | E73: Alfred Hitchcock | F73: 8.1 | H73: 206369 | I73: Reino Unido, EE.UU. | J73: Drama | K73: Crimen | M73: Un hombre planea un asesinato perfecto que sale mal. | N73: 0 | O73: 0 | P73: 0 | Q73: 0 | R73: 0 | S73: 0 | U73: =O73*4 + P73*2 + MAX(0,N73-O73-P73)*1 + Q73*0.2 + R73*2 + S73*1 + IF(T73="",0,IF(T73<=10,8,IF(T73<=50,6,IF(T73<=100,4,2)))) -> 0 | V73: Crimen perfecto (1954) es considerada una obra clave del cine de su época, y una pieza importante en la. | Y73: tt0046912
A74: El bueno, el feo y el malo | B74: 1966 | C74: 1960s | D74: 178 | E74: Sergio Leone | F74: 8.8 | G74: 7 | H74: 897462 | I74: Italia, España, EE.UU. | J74: Western | K74: Aventura | L74: Movistar Plus+ Ficción Total , FlixOlé, FlixOlé Amazon Channel | M74: Tres pistoleros compiten por un tesoro enterrado. | N74: 0 | O74: 0 | P74: 0 | Q74: 0 | R74: 0 | S74: 0 | T74: 169 | U74: =O74*4 + P74*2 + MAX(0,N74-O74-P74)*1 + Q74*0.2 + R74*2 + S74*1 + IF(T74="",0,IF(T74<=10,8,IF(T74<=50,6,IF(T74<=100,4,2)))) -> 2 | V74: El bueno, el feo y el malo (1966) definió para siempre el spaghetti western con su música, puesta en escena y. | W74: TOP 10-20 | Y74: tt0060196
A75: La delgada línea roja | B75: 1998 | C75: 1990s | D75: 170 | E75: Terrence Malick | F75: 7.6 | H75: 213327 | I75: EE.UU. | J75: Bélico | K75: Histórico | L75: Disney+ | M75: Soldados estadounidenses libran la batalla de Guadalcanal enfrentándose no solo al enemigo. | N75: 0 | O75: 0 | P75: 0 | Q75: 7 | R75: 1 | S75: 0 | U75: =O75*4 + P75*2 + MAX(0,N75-O75-P75)*1 + Q75*0.2 + R75*2 + S75*1 + IF(T75="",0,IF(T75<=10,8,IF(T75<=50,6,IF(T75<=100,4,2)))) -> 3.4 | Y75: tt0120863
A76: La gran evasión | B76: 1963 | C76: 1960s | D76: 172 | E76: John Sturges | F76: 8.2 | H76: 279289 | I76: EE.UU. | J76: Thriller | K76: Aventura | L76: Prime | M76: Prisioneros aliados planean una fuga masiva de un campo nazi. | N76: 0 | O76: 0 | P76: 0 | Q76: 1 | R76: 0 | S76: 0 | U76: =O76*4 + P76*2 + MAX(0,N76-O76-P76)*1 + Q76*0.2 + R76*2 + S76*1 + IF(T76="",0,IF(T76<=10,8,IF(T76<=50,6,IF(T76<=100,4,2)))) -> 0.2 | V76: La gran evasión (1963) es considerada una obra clave del cine de su época, y una pieza importante en la. | Y76: tt0057115
A77: Funny Games | B77: 1997 | C77: 1990s | D77: 108 | E77: Michael Haneke | F77: 7.5 | G77: 6 | H77: 98812 | I77: Austria | J77: Terror | K77: Asesino en serie | L77: Movistar, Movistar Plus+ Ficción Total , Acontra | M77: Anna, Georg y su hijo Georgie van a pasar las vacaciones a su bonita casa a orillas de un lago. | N77: 0 | O77: 0 | P77: 0 | Q77: 0 | R77: 0 | S77: 0 | U77: =O77*4 + P77*2 + MAX(0,N77-O77-P77)*1 + Q77*0.2 + R77*2 + S77*1 + IF(T77="",0,IF(T77<=10,8,IF(T77<=50,6,IF(T77<=100,4,2)))) -> 0 | Y77: tt0119167
A78: La princesa prometida | B78: 1987 | C78: 1980s | D78: 98 | E78: Rob Reiner | F78: 8 | H78: 489538 | I78: EE.UU. | J78: Aventura | K78: Familiar | L78: Disney+, Filmin, Lionsgate+ Amazon Channel, 3Cat | M78: Después de buscar fortuna durante cinco años, Westley (Cary Elwes) retorna a su tierra para. | N78: 0 | O78: 0 | P78: 0 | Q78: 1 | R78: 0 | S78: 0 | U78: =O78*4 + P78*2 + MAX(0,N78-O78-P78)*1 + Q78*0.2 + R78*2 + S78*1 + IF(T78="",0,IF(T78<=10,8,IF(T78<=50,6,IF(T78<=100,4,2)))) -> 0.2 | Y78: tt0093779
A79: ¿Qué fue de Baby Jane? | B79: 1962 | C79: 1960s | D79: 134 | E79: Robert Aldrich | F79: 8 | H79: 68178 | I79: EE.UU. | J79: Terror | K79: Thriller | M79: Dos hermanas viven aisladas mientras resurgen viejas rivalidades y locura. | N79: 1 | O79: 0 | P79: 0 | Q79: 5 | R79: 0 | S79: 0 | U79: =O79*4 + P79*2 + MAX(0,N79-O79-P79)*1 + Q79*0.2 + R79*2 + S79*1 + IF(T79="",0,IF(T79<=10,8,IF(T79<=50,6,IF(T79<=100,4,2)))) -> 2 | V79: ¿Qué fue de Baby Jane? | Y79: tt0056687
A80: Tiempos modernos | B80: 1936 | C80: 1930s | D80: 87 | E80: Charles Chaplin | F80: 8.5 | H80: 287076 | I80: EE.UU. | J80: Romance | K80: Comedia | L80: Acontra, Acontra Plus Amazon Channel, Tivify | M80: Un obrero lucha contra el trabajo moderno y sus dificultades sociales. | N80: 0 | O80: 0 | P80: 0 | Q80: 0 | R80: 0 | S80: 0 | T80: 78 | U80: =O80*4 + P80*2 + MAX(0,N80-O80-P80)*1 + Q80*0.2 + R80*2 + S80*1 + IF(T80="",0,IF(T80<=10,8,IF(T80<=50,6,IF(T80<=100,4,2)))) -> 4 | V80: Tiempos modernos (1936) es una crítica universal a la deshumanización del trabajo industrial y sigue siendo. | Y80: tt0027977
A81: Perversidad | B81: 1945 | C81: 1940s | D81: 102 | E81: Fritz Lang | F81: 7.7 | H81: 21549 | I81: EE.UU. | J81: Drama | K81: Noir | L81: Filmin, FlixOlé, Acontra, Acontra Plus Amazon Channel, Artiflix, JustWatch TV, Tivify, Plex, Runtime | M81: Un cajero bancario se enamora de una femme fatale que lo lleva a la ruina. | N81: 0 | O81: 0 | P81: 0 | Q81: 0 | R81: 0 | S81: 0 | U81: =O81*4 + P81*2 + MAX(0,N81-O81-P81)*1 + Q81*0.2 + R81*2 + S81*1 + IF(T81="",0,IF(T81<=10,8,IF(T81<=50,6,IF(T81<=100,4,2)))) -> 0 | V81: Perversidad (1945) es considerada una obra clave del cine de su época, y una pieza importante en la. | Y81: tt0038057
A82: Traffic | B82: 2000 | C82: 2000s | D82: 147 | E82: Steven Soderbergh | F82: 7.5 | G82: 7 | H82: 231618 | I82: EE.UU. | J82: Thriller | K82: Crimen | L82: Lionsgate+ Amazon Channel | M82: Varias historias conectadas muestran distintos frentes de la guerra contra las drogas. | N82: 4 | O82: 0 | P82: 1 | Q82: 5 | R82: 0 | S82: 0 | U82: =O82*4 + P82*2 + MAX(0,N82-O82-P82)*1 + Q82*0.2 + R82*2 + S82*1 + IF(T82="",0,IF(T82<=10,8,IF(T82<=50,6,IF(T82<=100,4,2)))) -> 6 | Y82: tt0181865
A83: Los lunes al sol | B83: 2002 | C83: 2000s | D83: 113 | E83: Fernando León de Aranoa | F83: 7.5 | H83: 16522 | I83: España | J83: Comedia | K83: Drama | L83: Filmin | M83: En una ciudad costera del norte de España, a la que el desarrollo industrial ha hecho crecer. | N83: 0 | O83: 0 | P83: 0 | Q83: 0 | R83: 0 | S83: 0 | U83: =O83*4 + P83*2 + MAX(0,N83-O83-P83)*1 + Q83*0.2 + R83*2 + S83*1 + IF(T83="",0,IF(T83<=10,8,IF(T83<=50,6,IF(T83<=100,4,2)))) -> 0 | Y83: tt0319769
A84: Tigre y dragón | B84: 2000 | C84: 2000s | D84: 120 | E84: Ang Lee | F84: 7.8 | H84: 296648 | I84: Taiwán, Hong Kong, China, EE.UU. | J84: Acción | K84: Aventura | L84: Netflix, Acontra, Acontra Plus Amazon Channel, Tivify | M84: Una espada legendaria robada desata una persecución donde se cruzan guerreros, amor prohibido. | N84: 4 | O84: 0 | P84: 0 | Q84: 10 | R84: 0 | S84: 0 | U84: =O84*4 + P84*2 + MAX(0,N84-O84-P84)*1 + Q84*0.2 + R84*2 + S84*1 + IF(T84="",0,IF(T84<=10,8,IF(T84<=50,6,IF(T84<=100,4,2)))) -> 6 | Y84: tt0190332
A85: Master and Commander | B85: 2003 | C85: 2000s | D85: 138 | E85: Peter Weir | F85: 7.5 | H85: 258421 | I85: EE.UU. | J85: Acción | K85: Aventura | L85: Disney+ | M85: Guerras napoleónicas, año 1805. | N85: 2 | O85: 0 | P85: 0 | Q85: 10 | R85: 0 | S85: 0 | U85: =O85*4 + P85*2 + MAX(0,N85-O85-P85)*1 + Q85*0.2 + R85*2 + S85*1 + IF(T85="",0,IF(T85<=10,8,IF(T85<=50,6,IF(T85<=100,4,2)))) -> 4 | Y85: tt0311113
A86: Toro Salvaje | B86: 1980 | C86: 1980s | D86: 129 | E86: Martin Scorsese | F86: 8.1 | H86: 412816 | I86: EE.UU. | J86: Drama | K86: Biográfico | L86: Prime, Movistar, Movistar Plus+ Ficción Total | M86: La vida del boxeador Jake LaMotta, marcada por su talento y su carácter autodestructivo dentro. | N86: 2 | O86: 0 | P86: 0 | Q86: 8 | R86: 0 | S86: 0 | T86: 129 | U86: =O86*4 + P86*2 + MAX(0,N86-O86-P86)*1 + Q86*0.2 + R86*2 + S86*1 + IF(T86="",0,IF(T86<=10,8,IF(T86<=50,6,IF(T86<=100,4,2)))) -> 5.6 | V86: Su montaje y coreografía de combate redefinieron el cine deportivo. | Y86: tt0081398
A87: Tarde de perros | B87: 1975 | C87: 1970s | D87: 125 | E87: Sidney Lumet | F87: 8 | G87: 6 | H87: 293577 | I87: EE.UU. | J87: Drama | K87: Crimen | L87: Movistar, Movistar Plus+ Ficción Total | M87: Un hombre desesperado intenta atracar un banco en Brooklyn para pagar una operación urgente. | N87: 1 | O87: 0 | P87: 0 | Q87: 6 | R87: 0 | S87: 0 | U87: =O87*4 + P87*2 + MAX(0,N87-O87-P87)*1 + Q87*0.2 + R87*2 + S87*1 + IF(T87="",0,IF(T87<=10,8,IF(T87<=50,6,IF(T87<=100,4,2)))) -> 2.2 | Y87: tt0072890
A88: The Artist | B88: 2011 | C88: 2010s | D88: 100 | E88: Michel Hazanavicius | F88: 7.8 | H88: 256131 | I88: Francia | J88: Romance | K88: Cine mudo | L88: Filmin, Acontra, Acontra Plus Amazon Channel, Tivify | M88: Hollywood, 1927. | N88: 5 | O88: 1 | P88: 1 | Q88: 10 | R88: 0 | S88: 1 | U88: =O88*4 + P88*2 + MAX(0,N88-O88-P88)*1 + Q88*0.2 + R88*2 + S88*1 + IF(T88="",0,IF(T88<=10,8,IF(T88<=50,6,IF(T88<=100,4,2)))) -> 12 | Y88: tt1655442
A89: El hombre elefante | B89: 1980 | C89: 1980s | D89: 124 | E89: David Lynch | F89: 8.2 | H89: 283471 | I89: Reino Unido | J89: Drama | K89: Biográfico | L89: Prime, Movistar, Movistar Plus+ Ficción Total , Filmin | M89: Joseph Merrick, un hombre con graves deformidades, lucha por ser tratado con dignidad en una. | N89: 0 | O89: 0 | P89: 0 | Q89: 8 | R89: 0 | S89: 0 | U89: =O89*4 + P89*2 + MAX(0,N89-O89-P89)*1 + Q89*0.2 + R89*2 + S89*1 + IF(T89="",0,IF(T89<=10,8,IF(T89<=50,6,IF(T89<=100,4,2)))) -> 1.6 | Y89: tt0080678
A90: Sed de mal | B90: 1958 | C90: 1950s | D90: 95 | E90: Orson Welles | F90: 7.9 | H90: 115384 | I90: EE.UU. | J90: Drama | K90: Noir | L90: Plex | M90: Un detective corrupto y un agente mexicano investigan un atentado. | N90: 0 | O90: 0 | P90: 0 | Q90: 0 | R90: 0 | S90: 0 | T90: 108 | U90: =O90*4 + P90*2 + MAX(0,N90-O90-P90)*1 + Q90*0.2 + R90*2 + S90*1 + IF(T90="",0,IF(T90<=10,8,IF(T90<=50,6,IF(T90<=100,4,2)))) -> 2 | V90: Sed de mal (1958) es considerada una obra clave del cine de su época, y una pieza importante en la. | Y90: tt0052311
A91: Encuentros en la tercera fase | B91: 1977 | C91: 1970s | D91: 138 | E91: Steven Spielberg | F91: 7.6 | H91: 237881 | I91: EE.UU. | J91: Ciencia ficción | K91: Drama | L91: Filmin, Tivify | M91: Un electricista es testigo de sucesos extraños tras el contacto con un OVNI. | N91: 2 | O91: 0 | P91: 0 | Q91: 9 | R91: 0 | S91: 0 | U91: =O91*4 + P91*2 + MAX(0,N91-O91-P91)*1 + Q91*0.2 + R91*2 + S91*1 + IF(T91="",0,IF(T91<=10,8,IF(T91<=50,6,IF(T91<=100,4,2)))) -> 3.8 | Y91: tt0075860
A92: Roma, ciudad abierta | B92: 1945 | C92: 1940s | D92: 103 | E92: Roberto Rossellini | F92: 8 | H92: 34329 | I92: Italia | J92: Bélico | K92: Thriller | L92: Prime, Movistar, Movistar Plus+ Ficción Total , Filmin, Artiflix | M92: La resistencia romana bajo la ocupación alemana. | N92: 0 | O92: 0 | P92: 0 | Q92: 1 | R92: 0 | S92: 0 | U92: =O92*4 + P92*2 + MAX(0,N92-O92-P92)*1 + Q92*0.2 + R92*2 + S92*1 + IF(T92="",0,IF(T92<=10,8,IF(T92<=50,6,IF(T92<=100,4,2)))) -> 0.2 | V92: Roma, ciudad abierta (1945) es fundacional del neorrealismo italiano y una de las primeras respuestas. | W92: Casi top | Y92: tt0038890
A93: La strada | B93: 1954 | C93: 1950s | D93: 108 | E93: Federico Fellini | F93: 8 | H93: 70277 | I93: Italia | J93: Drama | K93: Carcelario | L93: Filmin | M93: Una joven es vendida a un artista ambulante y busca su lugar. | N93: 1 | O93: 0 | P93: 0 | Q93: 2 | R93: 0 | S93: 0 | U93: =O93*4 + P93*2 + MAX(0,N93-O93-P93)*1 + Q93*0.2 + R93*2 + S93*1 + IF(T93="",0,IF(T93<=10,8,IF(T93<=50,6,IF(T93<=100,4,2)))) -> 1.4 | V93: La Strada (1954) consolidó a Fellini como autor internacional y es clave en el drama poético sobre personajes. | Y93: tt0047528
A94: Los inmortales | B94: 1986 | C94: 1980s | D94: 110 | E94: Russell Mulcahy | F94: 7 | H94: 160307 | I94: Reino Unido | J94: Fantasía | K94: Acción | L94: Prime, Movistar Plus+ Ficción Total , FlixOlé, FlixOlé Amazon Channel | M94: Un guerrero inmortal debe enfrentarse a otros inmortales en batallas decisivas, pues solo. | N94: 0 | O94: 0 | P94: 0 | Q94: 0 | R94: 0 | S94: 0 | U94: =O94*4 + P94*2 + MAX(0,N94-O94-P94)*1 + Q94*0.2 + R94*2 + S94*1 + IF(T94="",0,IF(T94<=10,8,IF(T94<=50,6,IF(T94<=100,4,2)))) -> 0 | Y94: tt0091203
A95: Érase una vez en América | B95: 1984 | C95: 1980s | D95: 229 | E95: Sergio Leone | F95: 8.3 | G95: 7 | H95: 410905 | I95: Italia, EE.UU. | J95: Drama | K95: Crimen | L95: Disney+, Tivify | M95: La vida de un grupo de amigos criminales a lo largo de varias décadas. | N95: 0 | O95: 0 | P95: 0 | Q95: 0 | R95: 0 | S95: 0 | T95: 157 | U95: =O95*4 + P95*2 + MAX(0,N95-O95-P95)*1 + Q95*0.2 + R95*2 + S95*1 + IF(T95="",0,IF(T95<=10,8,IF(T95<=50,6,IF(T95<=100,4,2)))) -> 2 | V95: Érase una vez en América (1984) es una épica criminal nostálgica que cerró la carrera de Leone y ha sido muy. | Y95: tt0087843
A96: Mi vida sin mí | B96: 2003 | C96: 2000s | D96: 106 | E96: Isabel Coixet | F96: 7.4 | H96: 26708 | I96: España | J96: Romance | K96: Drama | L96: Filmin | M96: Ann tiene 23 años, dos hijas, un marido que pasa más tiempo en paro que trabajando, una madre. | N96: 0 | O96: 0 | P96: 0 | Q96: 0 | R96: 0 | S96: 0 | U96: =O96*4 + P96*2 + MAX(0,N96-O96-P96)*1 + Q96*0.2 + R96*2 + S96*1 + IF(T96="",0,IF(T96<=10,8,IF(T96<=50,6,IF(T96<=100,4,2)))) -> 0 | Y96: tt0314412
A97: Bitelchús | B97: 1988 | C97: 1980s | D97: 92 | E97: Tim Burton | F97: 7.4 | H97: 421171 | I97: EE.UU. | J97: Fantasía | K97: Comedia | L97: Movistar Plus+ Ficción Total | M97: Un espíritu bromista especializado en sustos trata de expulsar a los nuevos ocupantes de una. | N97: 1 | O97: 0 | P97: 0 | Q97: 1 | R97: 0 | S97: 0 | U97: =O97*4 + P97*2 + MAX(0,N97-O97-P97)*1 + Q97*0.2 + R97*2 + S97*1 + IF(T97="",0,IF(T97<=10,8,IF(T97<=50,6,IF(T97<=100,4,2)))) -> 1.2 | Y97: tt0094721
A98: Perdida | B98: 2014 | C98: 2010s | D98: 149 | E98: David Fincher | F98: 8.1 | G98: 7 | H98: 1182358 | I98: EE.UU. | J98: Thriller | K98: Misterio | L98: Disney+ | M98: El día de su quinto aniversario de boda, Nick Dunne (Ben Affleck) informa que su esposa Amy. | N98: 0 | O98: 0 | P98: 0 | Q98: 1 | R98: 0 | S98: 0 | U98: =O98*4 + P98*2 + MAX(0,N98-O98-P98)*1 + Q98*0.2 + R98*2 + S98*1 + IF(T98="",0,IF(T98<=10,8,IF(T98<=50,6,IF(T98<=100,4,2)))) -> 0.2 | Y98: tt2267998
A99: Clerks | B99: 1994 | C99: 1990s | D99: 92 | E99: Kevin Smith | F99: 7.7 | H99: 241424 | I99: EE.UU. | J99: Comedia | M99: Narra en clave de humor la vida, amores y excentricidades de dos jóvenes cajeros de New Jersey. | N99: 0 | O99: 0 | P99: 0 | Q99: 0 | R99: 0 | S99: 0 | U99: =O99*4 + P99*2 + MAX(0,N99-O99-P99)*1 + Q99*0.2 + R99*2 + S99*1 + IF(T99="",0,IF(T99<=10,8,IF(T99<=50,6,IF(T99<=100,4,2)))) -> 0 | Y99: tt0109445
A100: Senderos de gloria | B100: 1957 | C100: 1950s | D100: 88 | E100: Stanley Kubrick | F100: 8.4 | G100: 7 | H100: 241836 | I100: EE.UU. | J100: Bélico | K100: Drama | L100: Movistar, Movistar Plus+ Ficción Total , MGM Plus Amazon Channel | M100: Un coronel debe liderar un ataque suicida durante la Primera Guerra Mundial. | N100: 0 | O100: 0 | P100: 0 | Q100: 0 | R100: 0 | S100: 0 | U100: =O100*4 + P100*2 + MAX(0,N100-O100-P100)*1 + Q100*0.2 + R100*2 + S100*1 + IF(T100="",0,IF(T100<=10,8,IF(T100<=50,6,IF(T100<=100,4,2)))) -> 0 | V100: Senderos de gloria (1957) es considerada una obra clave del género bélico, drama, y una pieza importante en. | Y100: tt0050825
...

Sheet Series
A1: Serie | B1: Año inicio | C1: Año fin | D1: Década | E1: Tipo | F1: Creador | G1: IMDb | H1: Mi nota | I1: Votos | J1: País | K1: Género | L1: Subgénero | M1: VOD (04/10/2026) | N1: Sinopsis | O1: Emmys | P1: Emmy Serie | Q1: Nom. Emmy | R1: Importancia histórica | S1: IMDb ID
A2: Breaking Bad | B2: 2008 | C2: 2013 | D2: 2000s | E2: Serie | F2: Michelle MacLaren, Adam Bernstein | G2: 9.5 | H2: 9 | I2: 2659109 | K2: Thriller | L2: Crimen | M2: Netflix | O2: 24 | P2: 1 | Q2: 114 | S2: tt0903747
A3: Juego de tronos | B3: 2011 | C3: 2019 | D3: 2010s | E3: Serie | F3: David Nutter, Alan Taylor | G3: 9.2 | H3: 10 | I3: 2648630 | K3: Fantasía | L3: Drama | M3: Movistar Plus+ Ficción Total , HBO Max | O3: 245 | P3: 1 | Q3: 466 | S3: tt0944947
A4: Stranger Things | B4: 2016 | C4: 2025 | D4: 2010s | E4: Serie | F4: Matt Duffer, Ross Duffer | G4: 8.6 | H4: 8 | I4: 1728260 | K4: Terror | L4: Fantasía | M4: Netflix | O4: 36 | P4: 0 | Q4: 113 | S4: tt4574334
A5: The Walking Dead | B5: 2010 | C5: 2022 | D5: 2010s | E5: Serie | F5: Greg Nicotero, Michael E. Satrazemis | G5: 8.1 | H5: 8 | I5: 1208602 | K5: Terror | L5: Thriller | M5: Netflix, Prime, Disney+, Movistar Plus+ Ficción Total , AMC+ Amazon Channel, AMC Plus Apple TV channel | O5: 14 | P5: 0 | Q5: 101 | S5: tt1520211
A6: Friends | B6: 1994 | C6: 2004 | D6: 1990s | E6: Serie | F6: Gary Halvorson, Kevin Bright | G6: 8.8 | I6: 1202980 | K6: Romance | L6: Comedia | M6: Netflix, Movistar Plus+ Ficción Total , HBO Max, Tivify, HBO Max Amazon Channel | O6: 2 | P6: 0 | Q6: 20 | S6: tt0108778
A7: Sherlock | B7: 2010 | C7: 2017 | D7: 2010s | E7: Serie | F7: Paul McGuigan, Jeremy Lovering | G7: 9 | H7: 7 | I7: 1096466 | K7: Drama | L7: Crimen | M7: Disney+ | O7: 14 | P7: 0 | Q7: 69 | S7: tt1475582
A8: Chernobyl | B8: 2019 | C8: 2019 | D8: 2010s | E8: Miniserie | F8: Johan Renck | G8: 9.3 | H8: 8 | I8: 1056716 | K8: Thriller | L8: Histórico | M8: Movistar Plus+ Ficción Total , HBO Max, HBO Max Amazon Channel | O8: 32 | P8: 1 | Q8: 49 | S8: tt7366338
A9: The Boys | B9: 2019 | C9: 2026 | D9: 2010s | E9: Serie | F9: Philip Sgriccia, Karen Gaviola | G9: 8.5 | H9: 9 | I9: 1017599 | K9: Acción | L9: Crimen | M9: Prime | O9: 0 | P9: 0 | Q9: 41 | S9: tt1190634
A10: Dexter | B10: 2006 | C10: 2013 | D10: 2000s | E10: Serie | F10: John Dahl, Steve Shill | G10: 8.6 | I10: 949478 | K10: Drama | L10: Crimen | M10: Netflix, Movistar Plus+ Ficción Total , SkyShowtime | O10: 7 | P10: 0 | Q10: 68 | S10: tt0773262
A11: Big Bang | B11: 2007 | C11: 2019 | D11: 2000s | E11: Serie | F11: Mark Cendrowski, Anthony Rich | G11: 8.1 | I11: 943333 | K11: Romance | L11: Comedia | M11: Movistar Plus+ Ficción Total , HBO Max, Tivify, HBO Max Amazon Channel | O11: 13 | P11: 0 | Q11: 130 | S11: tt0898266
A12: Better Call Saul | B12: 2015 | C12: 2022 | D12: 2010s | E12: Serie | F12: Vince Gilligan, Thomas Schnauz | G12: 9 | H12: 9 | I12: 855649 | K12: Drama | L12: Crimen | M12: Netflix | O12: 0 | P12: 0 | Q12: 122 | S12: tt3032476
A13: The Office | B13: 2005 | C13: 2013 | D13: 2000s | E13: Serie | F13: Paul Feig, Randall Einhorn | G13: 9 | H13: 10 | I13: 844701 | K13: Comedia | M13: Netflix, Prime, Disney+, Movistar Plus+ Ficción Total , SkyShowtime | O13: 6 | P13: 0 | Q13: 135 | S13: tt0386676
A14: Peaky Blinders | B14: 2013 | C14: 2022 | D14: 2010s | E14: Serie | F14: Anthony Byrne, Colm McCarthy | G14: 8.7 | H14: 9 | I14: 788117 | K14: Drama | L14: Crimen | M14: Netflix, Prime | O14: 0 | P14: 0 | Q14: 0 | S14: tt2442560
A15: Cómo conocí a vuestra madre | B15: 2005 | C15: 2014 | D15: 2000s | E15: Serie | F15: Pamela Fryman, Rob Greenberg | G15: 8.3 | H15: 8 | I15: 787329 | K15: Romance | L15: Comedia | M15: Disney+ | O15: 10 | P15: 0 | Q15: 53 | S15: tt0460649
A16: El juego del calamar | B16: 2021 | C16: 2025 | D16: 2020s | E16: Serie | F16: Hwang Dong-hyuk | G16: 7.9 | H16: 8 | I16: 772350 | K16: Acción | L16: Crimen | M16: Netflix | O16: 0 | P16: 0 | Q16: 0 | S16: tt10919420
A17: True Detective: Noche polar | B17: 2014 | D17: 2010s | E17: Serie | F17: Cary Joji Fukunaga, Issa López | G17: 8.8 | I17: 765168 | K17: Drama | L17: Crimen | M17: Movistar Plus+ Ficción Total , HBO Max, HBO Max Amazon Channel | O17: 0 | P17: 0 | Q17: 37 | S17: tt2356777
A18: Los últimos de nosotros | B18: 2023 | D18: 2020s | E18: Serie | F18: Craig Mazin, Neil Druckmann | G18: 8.4 | H18: 8 | I18: 746592 | K18: Acción | L18: Aventura | O18: 0 | P18: 0 | Q18: 0
A19: Black Mirror | B19: 2011 | D19: 2010s | E19: Serie | F19: Toby Haynes, Owen Harris | G19: 8.7 | H19: 9 | I19: 745407 | K19: Drama | L19: Crimen | M19: Netflix | O19: 0 | P19: 0 | Q19: 1 | S19: tt2085059
A20: Ataque a los titanes | B20: 2013 | C20: 2023 | D20: 2010s | E20: Serie | F20: Tetsurō Araki, Masashi Koizuka | G20: 9.1 | I20: 737873 | K20: Animación | L20: Acción | M20: Netflix, Prime, Crunchyroll, Crunchyroll Amazon Channel, Animebox Channel Amazon Channel | O20: 0 | P20: 0 | Q20: 0 | S20: tt2560140
A21: Rick y Morty | B21: 2013 | D21: 2010s | E21: Serie | F21: Wes Archer, Jacob Hair | G21: 9 | I21: 707560 | K21: Animación | L21: Aventura | M21: Netflix, Movistar Plus+ Ficción Total , HBO Max, HBO Max Amazon Channel | O21: 37 | P21: 0 | Q21: 41 | S21: tt2861424
A22: Perdidos | B22: 2004 | C22: 2010 | D22: 2000s | E22: Serie | F22: Jack Bender, Stephen Williams | G22: 8.3 | H22: 9 | I22: 679064 | K22: Fantasía | L22: Aventura | M22: Disney+ | O22: 9 | P22: 0 | Q22: 127 | S22: tt0411008
A23: Prison Break | B23: 2005 | C23: 2017 | D23: 2000s | E23: Serie | F23: Bobby Roth, Kevin Hooks | G23: 8.3 | I23: 676791 | K23: Acción | L23: Crimen | M23: Disney+ | O23: 0 | P23: 0 | Q23: 0 | S23: tt0455275
A24: Gambito de dama | B24: 2020 | C24: 2020 | D24: 2020s | E24: Miniserie | F24: Scott Frank | G24: 8.5 | H24: 6 | I24: 674068 | K24: Drama | M24: Netflix | O24: 34 | P24: 0 | Q24: 44 | S24: tt10048342
A25: The Mandalorian | B25: 2019 | C25: 2023 | D25: 2010s | E25: Serie | F25: Rick Famuyiwa, Bryce Dallas Howard | G25: 8.6 | H25: 10 | I25: 663211 | K25: Fantasía | L25: Acción | M25: Disney+ | O25: 54 | P25: 0 | Q25: 116 | S25: tt8111088
A26: Vikingos | B26: 2013 | C26: 2020 | D26: 2010s | E26: Serie | F26: Ciaran Donnelly, Ken Girotti | G26: 8.5 | H26: 8 | I26: 647472 | K26: Acción | L26: Aventura | M26: Netflix | O26: 9 | P26: 0 | Q26: 93 | S26: tt2306299
A27: The Witcher | B27: 2019 | D27: 2010s | E27: Serie | F27: Alex Garcia Lopez, Jeremy Webb | G27: 7.8 | H27: 7 | I27: 623459 | K27: Acción | L27: Aventura | M27: Netflix | O27: 0 | P27: 0 | Q27: 0 | S27: tt5180504
A28: La casa de papel | B28: 2017 | C28: 2021 | D28: 2010s | E28: Serie | F28: Jesús Colmenar, Alex Rodrigo | G28: 8.2 | I28: 615958 | K28: Acción | L28: Crimen | M28: Netflix, atresplayer | O28: 0 | P28: 0 | Q28: 0 | S28: tt6468322
A29: Hermanos de sangre | B29: 2001 | C29: 2001 | D29: 2000s | E29: Miniserie | F29: David Frankel, Mikael Salomon | G29: 9.4 | H29: 10 | I29: 601272 | K29: Acción | L29: Histórico | M29: Prime, HBO Max, HBO Max Amazon Channel | O29: 0 | P29: 0 | Q29: 0 | S29: tt0185906
A30: House | B30: 2004 | C30: 2012 | D30: 2000s | E30: Serie | F30: Greg Yaitanes, Deran Sarafian | G30: 8.7 | I30: 598198 | K30: Drama | M30: Netflix, Movistar Plus+ Ficción Total , SkyShowtime | O30: 11 | P30: 0 | Q30: 82 | S30: tt0412142
A31: Los Soprano | B31: 1999 | C31: 2007 | D31: 1990s | E31: Serie | F31: Timothy Van Patten, John Patterson | G31: 9.2 | I31: 591163 | K31: Drama | L31: Crimen | M31: Movistar Plus+ Ficción Total , HBO Max, HBO Max Amazon Channel | O31: 25 | P31: 1 | Q31: 47 | S31: tt0141842
A32: House of Cards | B32: 2013 | C32: 2018 | D32: 2010s | E32: Serie | F32: James Foley, Robin Wright | G32: 8.6 | H32: 9 | I32: 562047 | K32: Thriller | L32: Drama | M32: Netflix | O32: 7 | P32: 0 | Q32: 119 | S32: tt1856010
A33: La casa del dragón | B33: 2022 | D33: 2020s | E33: Serie | F33: Clare Kilner, Geeta Vasant Patel | G33: 8.3 | H33: 8 | I33: 560835 | K33: Acción | L33: Aventura | M33: Movistar Plus+ Ficción Total , HBO Max, HBO Max Amazon Channel | O33: 0 | P33: 0 | Q33: 0 | S33: tt11198330
A34: Westworld | B34: 2016 | C34: 2022 | D34: 2010s | E34: Serie | F34: Richard J. Lewis, Jonathan Nolan | G34: 8.4 | I34: 560086 | K34: Ciencia ficción | L34: Misterio | O34: 41 | P34: 0 | Q34: 207 | S34: tt0475784
A35: Dark | B35: 2017 | C35: 2020 | D35: 2010s | E35: Serie | F35: Baran bo Odar | G35: 8.7 | I35: 557436 | K35: Drama | L35: Crimen | M35: Netflix | O35: 0 | P35: 0 | Q35: 0 | S35: tt5753856
A36: Suits: La clave del éxito | B36: 2011 | C36: 2019 | D36: 2010s | E36: Serie | F36: Michael Smith, Anton Cropper | G36: 8.4 | I36: 546718 | K36: Comedia | L36: Drama | M36: Netflix, Prime, Movistar Plus+ Ficción Total , SkyShowtime | O36: 0 | P36: 0 | Q36: 0 | S36: tt1632701
A37: Sobrenatural | B37: 2005 | C37: 2020 | D37: 2000s | E37: Serie | F37: Robert Singer, Philip Sgriccia | G37: 8.4 | I37: 545519 | K37: Terror | L37: Fantasía | M37: Prime, Movistar Plus+ Ficción Total , HBO Max, HBO Max Amazon Channel | O37: 0 | P37: 0 | Q37: 10 | S37: tt0460681
A38: Modern Family | B38: 2009 | C38: 2020 | D38: 2000s | E38: Serie | F38: Gail Mancuso, Steven Levitan | G38: 8.5 | H38: 8 | I38: 545098 | K38: Romance | L38: Comedia | M38: Disney+ | O38: 71 | P38: 1 | Q38: 162 | S38: tt1442437
A39: Daredevil | B39: 2015 | C39: 2018 | D39: 2010s | E39: Serie | F39: Phil Abraham, Stephen Surjik | G39: 8.6 | I39: 538914 | K39: Acción | L39: Crimen | M39: Disney+ | O39: 0 | P39: 0 | Q39: 0 | S39: tt3322312
A40: Narcos | B40: 2015 | C40: 2017 | D40: 2010s | E40: Serie | F40: Andrés Baiz, Josef Kubota Wladyka | G40: 8.7 | H40: 8 | I40: 533791 | K40: Drama | L40: Crimen | M40: Netflix | O40: 0 | P40: 0 | Q40: 6 | S40: tt2707408
A41: Miércoles | B41: 2022 | D41: 2020s | E41: Serie | F41: Tim Burton, James Marshall | G41: 8 | I41: 505938 | K41: Fantasía | L41: Crimen | M41: Netflix | O41: 0 | P41: 0 | Q41: 0 | S41: tt13443470
A42: Death Note | B42: 2006 | C42: 2007 | D42: 2000s | E42: Serie | F42: Tetsurō Araki, Kei Tsunematsu | G42: 8.9 | I42: 494047 | K42: Animación | L42: Crimen | M42: Netflix, Crunchyroll, Crunchyroll Amazon Channel | O42: 0 | P42: 0 | Q42: 0 | S42: tt0877057
A43: Loki | B43: 2021 | C43: 2023 | D43: 2020s | E43: Serie | F43: Kate Herron, Justin Benson | G43: 8.2 | I43: 480820 | K43: Fantasía | L43: Acción | M43: Disney+ | O43: 0 | P43: 0 | Q43: 0 | S43: tt9140554
A44: Fargo | B44: 2014 | C44: 2024 | D44: 2010s | E44: Serie | F44: Noah Hawley, Michael Uppendahl | G44: 8.8 | I44: 473120 | K44: Thriller | L44: Crimen | M44: Netflix, Prime, Movistar, Movistar Plus+ Ficción Total , HBO Max, MGM Plus Amazon Channel, HBO Max Amazon Channel | O44: 8 | P44: 0 | Q44: 107 | S44: tt2802850
A45: Mr. Robot | B45: 2015 | C45: 2019 | D45: 2010s | E45: Serie | F45: Sam Esmail, Jim McKay | G45: 8.5 | H45: 8 | I45: 472706 | K45: Thriller | L45: Crimen | M45: Movistar Plus+ Ficción Total , SkyShowtime | O45: 7 | P45: 0 | Q45: 45 | S45: tt4158110
A46: Los Simpson | B46: 1989 | D46: 1980s | E46: Serie | F46: Mike B. Anderson, Jim Reardon | G46: 8.6 | H46: 8 | I46: 471493 | K46: Animación | L46: Comedia | M46: Disney+, Tivify | O46: 48 | P46: 0 | Q46: 192 | S46: tt0096697
A47: Arrow | B47: 2012 | C47: 2020 | D47: 2010s | E47: Serie | F47: James Bamford, John Behring | G47: 7.5 | I47: 462465 | K47: Acción | L47: Crimen | M47: Prime | O47: 0 | P47: 0 | Q47: 0 | S47: tt2193021
A48: Ted Lasso | B48: 2020 | D48: 2020s | E48: Serie | F48: Declan Lowney, MJ Delaney | G48: 8.7 | I48: 456780 | K48: Comedia | L48: Deportivo | M48: Apple TV, Apple TV Amazon Channel | O48: 19 | P48: 1 | Q48: 46 | S48: tt10986410
A49: Arcane | B49: 2021 | C49: 2024 | D49: 2020s | E49: Serie | F49: Pascal Charrue, Arnaud Delord | G49: 9 | I49: 453178 | K49: Animación | L49: Acción | M49: Netflix | O49: 0 | P49: 0 | Q49: 0 | S49: tt11126994
A50: Avatar. La leyenda de Aang | B50: 2005 | C50: 2008 | D50: 2000s | E50: Serie | F50: Oh Seung-hyun, Giancarlo Volpe | G50: 9.3 | I50: 452391 | K50: Animación | L50: Acción | M50: Netflix, Movistar Plus+ Ficción Total , SkyShowtime | O50: 0 | P50: 0 | Q50: 0 | S50: tt0417299
A51: South Park | B51: 1997 | D51: 1990s | E51: Serie | F51: Trey Parker, Eric Stough | G51: 8.7 | I51: 446958 | K51: Animación | L51: Comedia | M51: Movistar, Movistar Plus+ Ficción Total , fuboTV, Pluto TV | O51: 10 | P51: 0 | Q51: 54 | S51: tt0121955
A52: El señor de los anillos: Los anillos de poder | B52: 2022 | D52: 2020s | E52: Serie | F52: Charlotte Brändström, Sanaa Hamri | G52: 6.8 | H52: 7 | I52: 442905 | K52: Acción | L52: Aventura | M52: Prime | O52: 0 | P52: 0 | Q52: 0 | S52: tt7631058
A53: The Wire (Bajo escucha) | B53: 2002 | C53: 2008 | D53: 2000s | E53: Serie | F53: Joe Chappelle, Ernest Dickerson | G53: 9.3 | I53: 436597 | K53: Thriller | L53: Crimen | M53: Movistar Plus+ Ficción Total , HBO Max, HBO Max Amazon Channel | O53: 0 | P53: 0 | Q53: 2 | S53: tt0306414
A54: Brooklyn Nine-Nine | B54: 2013 | C54: 2021 | D54: 2010s | E54: Serie | F54: Michael McDonald, Claire Scanlon | G54: 8.4 | I54: 421812 | K54: Comedia | L54: Crimen | M54: Netflix, Movistar Plus+ Ficción Total , SkyShowtime | O54: 1 | P54: 0 | Q54: 10 | S54: tt2467372
A55: Bruja Escarlata y Visión | B55: 2021 | C55: 2021 | D55: 2020s | E55: Miniserie | F55: Matt Shakman | G55: 7.9 | I55: 421712 | K55: Acción | L55: Comedia | M55: Disney+ | O55: 9 | P55: 0 | Q55: 81 | S55: tt9140560
A56: Mindhunter | B56: 2017 | C56: 2019 | D56: 2010s | E56: Serie | F56: David Fincher, Carl Franklin | G56: 8.6 | I56: 403239 | K56: Drama | L56: Crimen | M56: Netflix | O56: 0 | P56: 0 | Q56: 2 | S56: tt5290382
A57: Sex Education | B57: 2019 | C57: 2023 | D57: 2010s | E57: Serie | F57: Ben Taylor, Kate Herron | G57: 8.2 | I57: 402198 | K57: Romance | L57: Comedia | M57: Netflix | O57: 0 | P57: 0 | Q57: 0 | S57: tt7767422
A58: Separación | B58: 2022 | D58: 2020s | E58: Serie | F58: Ben Stiller, Aoife McArdle | G58: 8.6 | I58: 401269 | K58: Ciencia ficción | L58: Misterio | M58: Apple TV, Apple TV Amazon Channel | O58: 0 | P58: 0 | Q58: 0 | S58: tt11280740
A59: Fallout | B59: 2024 | D59: 2020s | E59: Serie | F59: Frederick E.O. Toye, Jonathan Nolan | G59: 8.3 | I59: 400469 | K59: Acción | L59: Aventura | M59: Prime | O59: 0 | P59: 0 | Q59: 0 | S59: tt12637874
A60: Ozark | B60: 2017 | C60: 2022 | D60: 2010s | E60: Serie | F60: Jason Bateman, Alik Sakharov | G60: 8.4 | I60: 396842 | K60: Thriller | L60: Crimen | M60: Netflix | O60: 3 | P60: 0 | Q60: 72 | S60: tt5071412
A61: Lucifer | B61: 2016 | C61: 2021 | D61: 2010s | E61: Serie | F61: Nathan Hope, Eagle Egilsson | G61: 8 | I61: 396218 | K61: Fantasía | L61: Crimen | M61: Netflix, Movistar, Movistar Plus+ Ficción Total | O61: 0 | P61: 0 | Q61: 1 | S61: tt4052886
A62: Padre de familia | B62: 1999 | D62: 1990s | E62: Serie | F62: James Purdum, Dominic Bianchi | G62: 8.1 | H62: 8 | I62: 391095 | K62: Animación | L62: Comedia | M62: Disney+ | O62: 6 | P62: 0 | Q62: 38 | S62: tt0182576
A63: The Flash | B63: 2014 | C63: 2023 | D63: 2010s | E63: Serie | F63: Stefan Pleszczynski, David McWhirter | G63: 7.5 | I63: 387751 | K63: Acción | L63: Aventura | M63: Prime | O63: 0 | P63: 0 | Q63: 9 | S63: tt3107288
A64: Seinfeld | B64: 1989 | C64: 1998 | D64: 1980s | E64: Serie | F64: Andy Ackerman, Tom Cherones | G64: 8.8 | I64: 387445 | K64: Comedia | M64: Netflix | O64: 4 | P64: 0 | Q64: 22 | S64: tt0098904
A65: Crónicas vampíricas | B65: 2009 | C65: 2017 | D65: 2000s | E65: Serie | F65: Chris Grismer, Joshua Butler | G65: 7.7 | I65: 387349 | K65: Terror | L65: Fantasía | M65: Netflix, Prime, Movistar Plus+ Ficción Total , HBO Max, HBO Max Amazon Channel | O65: 0 | P65: 0 | Q65: 0 | S65: tt1405406
A66: Homeland | B66: 2011 | C66: 2020 | D66: 2010s | E66: Serie | F66: Lesli Linka Glatter, Michael Cuesta | G66: 8.3 | I66: 387142 | K66: Drama | L66: Crimen | M66: Netflix, Prime, Disney+ | O66: 24 | P66: 1 | Q66: 104 | S66: tt1796960
A67: Anatomía de Grey | B67: 2005 | D67: 2000s | E67: Serie | F67: Kevin McKidd, Debbie Allen | G67: 7.6 | I67: 376669 | K67: Romance | L67: Drama | M67: Disney+ | O67: 11 | P67: 0 | Q67: 91 | S67: tt0413573
A68: You | B68: 2018 | C68: 2025 | D68: 2010s | E68: Serie | F68: Silver Tree, Marcos Siega | G68: 7.6 | I68: 373447 | K68: Romance | L68: Crimen | M68: Netflix | O68: 0 | P68: 0 | Q68: 0 | S68: tt7335184
A69: Succession | B69: 2018 | C69: 2023 | D69: 2010s | E69: Serie | F69: Mark Mylod, Andrij Parekh | G69: 8.8 | H69: 10 | I69: 364140 | K69: Comedia | L69: Drama | M69: Movistar Plus+ Ficción Total , HBO Max, HBO Max Amazon Channel | O69: 25 | P69: 1 | Q69: 57 | S69: tt7660850
A70: American Horror Story: Asylum | B70: 2011 | D70: 2010s | E70: Serie | F70: Bradley Buecker, Alfonso Gomez-Rejon | G70: 7.9 | H70: 8 | I70: 365171 | K70: Terror | L70: Ciencia ficción | M70: Disney+ | O70: 6 | P70: 0 | Q70: 54 | S70: tt1844624
A71: One Piece | B71: 1999 | D71: 1990s | E71: Serie | F71: Munehisa Sakai, Kōnosuke Uda | G71: 9 | I71: 362121 | K71: Animación | L71: Acción | M71: Netflix, Disney+, Crunchyroll, Crunchyroll Amazon Channel, Animebox Channel Amazon Channel, 3Cat | O71: 0 | P71: 0 | Q71: 0 | S71: tt0388629
A72: Hijos de la anarquía | B72: 2008 | C72: 2014 | D72: 2000s | E72: Serie | F72: Paris Barclay, Guy Ferland | G72: 8.5 | H72: 8 | I72: 358619 | K72: Thriller | L72: Crimen | M72: Disney+ | O72: 0 | P72: 0 | Q72: 12 | S72: tt1124373
A73: Invincible | B73: 2021 | D73: 2020s | E73: Serie | F73: Dan Duncan, Shaun O'Neil | G73: 8.7 | I73: 349986 | K73: Animación | L73: Acción | M73: Prime | O73: 0 | P73: 0 | Q73: 0 | S73: tt6741278
A74: Arrested Development | B74: 2003 | C74: 2019 | D74: 2000s | E74: Serie | F74: Troy Miller, Mitchell Hurwitz | G74: 8.6 | I74: 345772 | K74: Comedia | M74: Netflix, Disney+ | O74: 0 | P74: 0 | Q74: 15 | S74: tt0367279
A75: Por trece razones | B75: 2017 | C75: 2020 | D75: 2010s | E75: Serie | F75: Jessica Yu, Kyle Patrick Alvarez | G75: 7.4 | I75: 342187 | K75: Thriller | L75: Misterio | M75: Netflix | O75: 0 | P75: 0 | Q75: 5 | S75: tt1837492
A76: Orange Is the New Black | B76: 2013 | C76: 2019 | D76: 2010s | E76: Serie | F76: Andrew McCarthy, Phil Abraham | G76: 8 | I76: 337850 | K76: Comedia | L76: Crimen | M76: Netflix | O76: 2 | P76: 0 | Q76: 20 | S76: tt2372162
A77: Shameless | B77: 2011 | C77: 2021 | D77: 2010s | E77: Serie | F77: Iain B. MacDonald, Mark Mylod | G77: 8.5 | I77: 336853 | K77: Comedia | L77: Drama | M77: Netflix, Prime, Movistar Plus+ Ficción Total , HBO Max, HBO Max Amazon Channel | O77: 4 | P77: 0 | Q77: 15 | S77: tt1586680
A78: La maldición de Hill House | B78: 2018 | C78: 2018 | D78: 2010s | E78: Miniserie | F78: Mike Flanagan | G78: 8.5 | H78: 8 | I78: 334098 | K78: Terror | L78: Misterio | M78: Netflix | O78: 0 | P78: 0 | Q78: 0 | S78: tt6763664
A79: The White Lotus | B79: 2021 | D79: 2020s | E79: Serie | F79: Mike White | G79: 8 | I79: 331453 | K79: Comedia | L79: Misterio | M79: Movistar Plus+ Ficción Total , HBO Max, HBO Max Amazon Channel | O79: 0 | P79: 0 | Q79: 0 | S79: tt13406094
A80: Euphoria | B80: 2019 | C80: 2026 | D80: 2010s | E80: Serie | F80: Sam Levinson, Pippa Bianco | G80: 8.1 | I80: 321906 | K80: Drama | M80: Movistar Plus+ Ficción Total , HBO Max, HBO Max Amazon Channel | O80: 5 | P80: 0 | Q80: 17 | S80: tt8772296
A81: The Bear | B81: 2022 | C81: 2026 | D81: 2020s | E81: Serie | F81: Christopher Storer, Joanna Calo | G81: 8.5 | I81: 321626 | K81: Comedia | L81: Drama | M81: Disney+ | O81: 0 | P81: 0 | Q81: 0 | S81: tt14452776
A82: Aspirantes | B82: 2021 | D82: 2020s | E82: Serie | F82: Apoorv Singh Karki, Deepesh Sumitra Jagdish | G82: 9.1 | I82: 319587 | K82: Drama | O82: 0 | P82: 0 | Q82: 0
A83: Yellowstone | B83: 2018 | C83: 2024 | D83: 2010s | E83: Serie | F83: Stephen Kay, Taylor Sheridan | G83: 8.6 | I83: 318928 | K83: Western | L83: Drama | M83: Netflix, Prime, Movistar Plus+ Ficción Total , SkyShowtime | O83: 0 | P83: 0 | Q83: 3 | S83: tt4236770
A84: Parks and Recreation | B84: 2009 | C84: 2015 | D84: 2000s | E84: Serie | F84: Dean Holland, Michael Schur | G84: 8.6 | I84: 318065 | K84: Comedia | O84: 0 | P84: 0 | Q84: 36 | S84: tt1266020
A85: Caballero Luna | B85: 2022 | C85: 2022 | D85: 2020s | E85: Miniserie | F85: Mohamed Diab, Justin Benson | G85: 7.3 | I85: 317059 | K85: Fantasía | L85: Acción | M85: Disney+ | O85: 0 | P85: 0 | Q85: 0 | S85: tt10234724
A86: The Umbrella Academy | B86: 2019 | C86: 2024 | D86: 2010s | E86: Serie | F86: Jeremy Webb, Paco Cabezas | G86: 7.8 | I86: 317050 | K86: Acción | L86: Aventura | M86: Netflix | O86: 0 | P86: 0 | Q86: 34 | S86: tt1312171
A87: Community | B87: 2009 | C87: 2015 | D87: 2000s | E87: Serie | F87: Tristram Shapeero, Joe Russo | G87: 8.5 | I87: 313433 | K87: Comedia | M87: Netflix | O87: 1 | P87: 0 | Q87: 3 | S87: tt1439629
A88: Adolescencia | B88: 2025 | C88: 2025 | D88: 2020s | E88: Miniserie | F88: Philip Barantini | G88: 8.1 | I88: 312992 | K88: Thriller | L88: Crimen | M88: Netflix | O88: 0 | P88: 0 | Q88: 0 | S88: tt31806037
A89: Hannibal | B89: 2013 | C89: 2015 | D89: 2010s | E89: Serie | F89: Michael Rymer, Guillermo Navarro | G89: 8.5 | I89: 312504 | K89: Terror | L89: Crimen | M89: Filmin | O89: 0 | P89: 0 | Q89: 7 | S89: tt2243973
A90: The Punisher | B90: 2017 | C90: 2019 | D90: 2010s | E90: Serie | F90: Jim O'Hanlon, Jeremy Webb | G90: 8.4 | I90: 310980 | K90: Acción | L90: Crimen | M90: Disney+ | O90: 0 | P90: 0 | Q90: 0 | S90: tt5675620
A91: Los 100 | B91: 2014 | C91: 2020 | D91: 2010s | E91: Serie | F91: Dean White, Ed Fraiman | G91: 7.5 | I91: 306800 | K91: Acción | L91: Misterio | M91: Prime | O91: 0 | P91: 0 | Q91: 0 | S91: tt2661044
A92: Firefly | B92: 2002 | C92: 2003 | D92: 2000s | E92: Serie | F92: Joss Whedon, Vern Gillum | G92: 8.9 | I92: 303480 | K92: Ciencia ficción | L92: Aventura | O92: 0 | P92: 0 | Q92: 0 | S92: tt0303461
A93: El cuento de la criada | B93: 2017 | C93: 2025 | D93: 2010s | E93: Serie | F93: Mike Barker, Elisabeth Moss | G93: 8.3 | I93: 303209 | K93: Ciencia ficción | L93: Thriller | M93: Netflix, Prime, Disney+, Movistar Plus+ Ficción Total , HBO Max, MGM Plus Amazon Channel, HBO Max Amazon Channel | O93: 36 | P93: 1 | Q93: 205 | S93: tt5834204
A94: The Blacklist | B94: 2013 | C94: 2023 | D94: 2010s | E94: Serie | F94: Andrew McCarthy, Michael W. Watkins | G94: 7.9 | I94: 302987 | K94: Drama | L94: Crimen | M94: Netflix, Tivify | O94: 0 | P94: 0 | Q94: 7 | S94: tt2741602
A95: Reacher | B95: 2022 | D95: 2020s | E95: Serie | F95: Sam Hill, Omar Madha | G95: 8 | I95: 302356 | K95: Acción | L95: Crimen | M95: Prime | O95: 0 | P95: 0 | Q95: 0 | S95: tt9288030
A96: Dos hombres y medio | B96: 2003 | C96: 2015 | D96: 2000s | E96: Serie | F96: James Widdoes, Gary Halvorson | G96: 7.1 | I96: 300084 | K96: Romance | L96: Comedia | M96: Prime | O96: 7 | P96: 0 | Q96: 77 | S96: tt0369179
A97: Spartacus: Sangre y arena | B97: 2010 | C97: 2013 | D97: 2010s | E97: Serie | F97: Jesse Warn, Michael Hurst | G97: 8.4 | H97: 8 | I97: 298168 | K97: Acción | L97: Biográfico | M97: Netflix, MGM Plus Amazon Channel | O97: 0 | P97: 0 | Q97: 0 | S97: tt1442449
A98: Mad Men | B98: 2007 | C98: 2015 | D98: 2000s | E98: Serie | F98: Phil Abraham, Michael Uppendahl | G98: 8.7 | I98: 293149 | K98: Drama | M98: Disney+, Lionsgate+ Amazon Channel | O98: 48 | P98: 1 | Q98: 225 | S98: tt0804503
A99: Scrubs | B99: 2001 | C99: 2010 | D99: 2000s | E99: Serie | F99: Michael Spiller, Bill Lawrence | G99: 8.4 | I99: 287148 | K99: Comedia | L99: Drama | M99: Disney+ | O99: 3 | P99: 0 | Q99: 15 | S99: tt0285403
A100: Falcon y el Soldado de Invierno | B100: 2021 | C100: 2021 | D100: 2020s | E100: Miniserie | F100: Kari Skogland | G100: 7.1 | I100: 284447 | K100: Acción | L100: Aventura | M100: Disney+ | O100: 0 | P100: 0 | Q100: 29 | S100: tt9208876
...

Sheet Análisis
A1: RESUMEN
A2: Películas en la lista | B2: =COUNTA('Movie Data Base by Keizar'!A2:A4000) -> 2382
A3: Vistas (con tu nota) | B3: =COUNT('Movie Data Base by Keizar'!G2:G4000) -> 1285
A4: Tu nota media | B4: =ROUND(AVERAGE('Movie Data Base by Keizar'!G2:G4000),2) -> 6.26
A5: Nota media IMDb (vistas) | B5: =ROUND(AVERAGEIF('Movie Data Base by Keizar'!G2:G4000,">0",'Movie Data Base by Keizar'!F2:F4000),2) -> 6.9
A6: Horas vistas (aprox.) | B6: =ROUND(SUMIF('Movie Data Base by Keizar'!G2:G4000,">0",'Movie Data Base by Keizar'!D2:D4000)/60,0) -> 2457
A7: Duración media (min) | B7: =ROUND(AVERAGE('Movie Data Base by Keizar'!D2:D4000),0) -> 117
A10: POR GÉNERO | F10: POR DÉCADA | K10: TUS NOTAS
A11: Género | B11: En lista | C11: Vistas | D11: Tu media | F11: Década | G11: En lista | H11: Vistas | I11: Tu media | K11: Nota | L11: Nº pelis
A12: Drama | B12: =COUNTIF('Movie Data Base by Keizar'!J:J,A12) -> 428 | C12: =COUNTIFS('Movie Data Base by Keizar'!J:J,A12,'Movie Data Base by Keizar'!G:G,">0") -> 117 | D12: =IFERROR(ROUND(AVERAGEIFS('Movie Data Base by Keizar'!G:G,'Movie Data Base by Keizar'!J:J,A12,'Movie Data Base by Keizar'!G:G,">0"),2),"") -> 6.93 | F12: 1920s | G12: =COUNTIF('Movie Data Base by Keizar'!C:C,F12) -> 15 | H12: =COUNTIFS('Movie Data Base by Keizar'!C:C,F12,'Movie Data Base by Keizar'!G:G,">0") -> 1 | I12: =IFERROR(ROUND(AVERAGEIFS('Movie Data Base by Keizar'!G:G,'Movie Data Base by Keizar'!C:C,F12,'Movie Data Base by Keizar'!G:G,">0"),2),"") -> 6 | K12: 10 | L12: =COUNTIF('Movie Data Base by Keizar'!G:G,K12) -> 7
A13: Thriller | B13: =COUNTIF('Movie Data Base by Keizar'!J:J,A13) -> 279 | C13: =COUNTIFS('Movie Data Base by Keizar'!J:J,A13,'Movie Data Base by Keizar'!G:G,">0") -> 194 | D13: =IFERROR(ROUND(AVERAGEIFS('Movie Data Base by Keizar'!G:G,'Movie Data Base by Keizar'!J:J,A13,'Movie Data Base by Keizar'!G:G,">0"),2),"") -> 6.43 | F13: 1930s | G13: =COUNTIF('Movie Data Base by Keizar'!C:C,F13) -> 17 | H13: =COUNTIFS('Movie Data Base by Keizar'!C:C,F13,'Movie Data Base by Keizar'!G:G,">0") -> 0 | I13: =IFERROR(ROUND(AVERAGEIFS('Movie Data Base by Keizar'!G:G,'Movie Data Base by Keizar'!C:C,F13,'Movie Data Base by Keizar'!G:G,">0"),2),"") | K13: 9 | L13: =COUNTIF('Movie Data Base by Keizar'!G:G,K13) -> 56
A14: Romance | B14: =COUNTIF('Movie Data Base by Keizar'!J:J,A14) -> 236 | C14: =COUNTIFS('Movie Data Base by Keizar'!J:J,A14,'Movie Data Base by Keizar'!G:G,">0") -> 68 | D14: =IFERROR(ROUND(AVERAGEIFS('Movie Data Base by Keizar'!G:G,'Movie Data Base by Keizar'!J:J,A14,'Movie Data Base by Keizar'!G:G,">0"),2),"") -> 5.96 | F14: 1940s | G14: =COUNTIF('Movie Data Base by Keizar'!C:C,F14) -> 31 | H14: =COUNTIFS('Movie Data Base by Keizar'!C:C,F14,'Movie Data Base by Keizar'!G:G,">0") -> 1 | I14: =IFERROR(ROUND(AVERAGEIFS('Movie Data Base by Keizar'!G:G,'Movie Data Base by Keizar'!C:C,F14,'Movie Data Base by Keizar'!G:G,">0"),2),"") -> 7 | K14: 8 | L14: =COUNTIF('Movie Data Base by Keizar'!G:G,K14) -> 196
A15: Acción | B15: =COUNTIF('Movie Data Base by Keizar'!J:J,A15) -> 214 | C15: =COUNTIFS('Movie Data Base by Keizar'!J:J,A15,'Movie Data Base by Keizar'!G:G,">0") -> 182 | D15: =IFERROR(ROUND(AVERAGEIFS('Movie Data Base by Keizar'!G:G,'Movie Data Base by Keizar'!J:J,A15,'Movie Data Base by Keizar'!G:G,">0"),2),"") -> 5.97 | F15: 1950s | G15: =COUNTIF('Movie Data Base by Keizar'!C:C,F15) -> 44 | H15: =COUNTIFS('Movie Data Base by Keizar'!C:C,F15,'Movie Data Base by Keizar'!G:G,">0") -> 3 | I15: =IFERROR(ROUND(AVERAGEIFS('Movie Data Base by Keizar'!G:G,'Movie Data Base by Keizar'!C:C,F15,'Movie Data Base by Keizar'!G:G,">0"),2),"") -> 7.33 | K15: 7 | L15: =COUNTIF('Movie Data Base by Keizar'!G:G,K15) -> 333
A16: Terror | B16: =COUNTIF('Movie Data Base by Keizar'!J:J,A16) -> 203 | C16: =COUNTIFS('Movie Data Base by Keizar'!J:J,A16,'Movie Data Base by Keizar'!G:G,">0") -> 176 | D16: =IFERROR(ROUND(AVERAGEIFS('Movie Data Base by Keizar'!G:G,'Movie Data Base by Keizar'!J:J,A16,'Movie Data Base by Keizar'!G:G,">0"),2),"") -> 5.89 | F16: 1960s | G16: =COUNTIF('Movie Data Base by Keizar'!C:C,F16) -> 57 | H16: =COUNTIFS('Movie Data Base by Keizar'!C:C,F16,'Movie Data Base by Keizar'!G:G,">0") -> 6 | I16: =IFERROR(ROUND(AVERAGEIFS('Movie Data Base by Keizar'!G:G,'Movie Data Base by Keizar'!C:C,F16,'Movie Data Base by Keizar'!G:G,">0"),2),"") -> 7 | K16: 6 | L16: =COUNTIF('Movie Data Base by Keizar'!G:G,K16) -> 362
A17: Comedia | B17: =COUNTIF('Movie Data Base by Keizar'!J:J,A17) -> 199 | C17: =COUNTIFS('Movie Data Base by Keizar'!J:J,A17,'Movie Data Base by Keizar'!G:G,">0") -> 101 | D17: =IFERROR(ROUND(AVERAGEIFS('Movie Data Base by Keizar'!G:G,'Movie Data Base by Keizar'!J:J,A17,'Movie Data Base by Keizar'!G:G,">0"),2),"") -> 6.28 | F17: 1970s | G17: =COUNTIF('Movie Data Base by Keizar'!C:C,F17) -> 82 | H17: =COUNTIFS('Movie Data Base by Keizar'!C:C,F17,'Movie Data Base by Keizar'!G:G,">0") -> 21 | I17: =IFERROR(ROUND(AVERAGEIFS('Movie Data Base by Keizar'!G:G,'Movie Data Base by Keizar'!C:C,F17,'Movie Data Base by Keizar'!G:G,">0"),2),"") -> 7.52 | K17: 5 | L17: =COUNTIF('Movie Data Base by Keizar'!G:G,K17) -> 172
A18: Animación | B18: =COUNTIF('Movie Data Base by Keizar'!J:J,A18) -> 182 | C18: =COUNTIFS('Movie Data Base by Keizar'!J:J,A18,'Movie Data Base by Keizar'!G:G,">0") -> 92 | D18: =IFERROR(ROUND(AVERAGEIFS('Movie Data Base by Keizar'!G:G,'Movie Data Base by Keizar'!J:J,A18,'Movie Data Base by Keizar'!G:G,">0"),2),"") -> 6.24 | F18: 1980s | G18: =COUNTIF('Movie Data Base by Keizar'!C:C,F18) -> 130 | H18: =COUNTIFS('Movie Data Base by Keizar'!C:C,F18,'Movie Data Base by Keizar'!G:G,">0") -> 40 | I18: =IFERROR(ROUND(AVERAGEIFS('Movie Data Base by Keizar'!G:G,'Movie Data Base by Keizar'!C:C,F18,'Movie Data Base by Keizar'!G:G,">0"),2),"") -> 6.55 | K18: 4 | L18: =COUNTIF('Movie Data Base by Keizar'!G:G,K18) -> 85
A19: Ciencia ficción | B19: =COUNTIF('Movie Data Base by Keizar'!J:J,A19) -> 161 | C19: =COUNTIFS('Movie Data Base by Keizar'!J:J,A19,'Movie Data Base by Keizar'!G:G,">0") -> 144 | D19: =IFERROR(ROUND(AVERAGEIFS('Movie Data Base by Keizar'!G:G,'Movie Data Base by Keizar'!J:J,A19,'Movie Data Base by Keizar'!G:G,">0"),2),"") -> 6.25 | F19: 1990s | G19: =COUNTIF('Movie Data Base by Keizar'!C:C,F19) -> 263 | H19: =COUNTIFS('Movie Data Base by Keizar'!C:C,F19,'Movie Data Base by Keizar'!G:G,">0") -> 134 | I19: =IFERROR(ROUND(AVERAGEIFS('Movie Data Base by Keizar'!G:G,'Movie Data Base by Keizar'!C:C,F19,'Movie Data Base by Keizar'!G:G,">0"),2),"") -> 6.93 | K19: 3 | L19: =COUNTIF('Movie Data Base by Keizar'!G:G,K19) -> 53
A20: Fantasía | B20: =COUNTIF('Movie Data Base by Keizar'!J:J,A20) -> 140 | C20: =COUNTIFS('Movie Data Base by Keizar'!J:J,A20,'Movie Data Base by Keizar'!G:G,">0") -> 100 | D20: =IFERROR(ROUND(AVERAGEIFS('Movie Data Base by Keizar'!G:G,'Movie Data Base by Keizar'!J:J,A20,'Movie Data Base by Keizar'!G:G,">0"),2),"") -> 6.19 | F20: 2000s | G20: =COUNTIF('Movie Data Base by Keizar'!C:C,F20) -> 744 | H20: =COUNTIFS('Movie Data Base by Keizar'!C:C,F20,'Movie Data Base by Keizar'!G:G,">0") -> 434 | I20: =IFERROR(ROUND(AVERAGEIFS('Movie Data Base by Keizar'!G:G,'Movie Data Base by Keizar'!C:C,F20,'Movie Data Base by Keizar'!G:G,">0"),2),"") -> 6.38 | K20: 2 | L20: =COUNTIF('Movie Data Base by Keizar'!G:G,K20) -> 16
A21: Bélico | B21: =COUNTIF('Movie Data Base by Keizar'!J:J,A21) -> 81 | C21: =COUNTIFS('Movie Data Base by Keizar'!J:J,A21,'Movie Data Base by Keizar'!G:G,">0") -> 22 | D21: =IFERROR(ROUND(AVERAGEIFS('Movie Data Base by Keizar'!G:G,'Movie Data Base by Keizar'!J:J,A21,'Movie Data Base by Keizar'!G:G,">0"),2),"") -> 7.14 | F21: 2010s | G21: =COUNTIF('Movie Data Base by Keizar'!C:C,F21) -> 759 | H21: =COUNTIFS('Movie Data Base by Keizar'!C:C,F21,'Movie Data Base by Keizar'!G:G,">0") -> 522 | I21: =IFERROR(ROUND(AVERAGEIFS('Movie Data Base by Keizar'!G:G,'Movie Data Base by Keizar'!C:C,F21,'Movie Data Base by Keizar'!G:G,">0"),2),"") -> 5.92 | K21: 1 | L21: =COUNTIF('Movie Data Base by Keizar'!G:G,K21) -> 5
A22: Musical | B22: =COUNTIF('Movie Data Base by Keizar'!J:J,A22) -> 79 | C22: =COUNTIFS('Movie Data Base by Keizar'!J:J,A22,'Movie Data Base by Keizar'!G:G,">0") -> 26 | D22: =IFERROR(ROUND(AVERAGEIFS('Movie Data Base by Keizar'!G:G,'Movie Data Base by Keizar'!J:J,A22,'Movie Data Base by Keizar'!G:G,">0"),2),"") -> 6.15 | F22: 2020s | G22: =COUNTIF('Movie Data Base by Keizar'!C:C,F22) -> 239 | H22: =COUNTIFS('Movie Data Base by Keizar'!C:C,F22,'Movie Data Base by Keizar'!G:G,">0") -> 123 | I22: =IFERROR(ROUND(AVERAGEIFS('Movie Data Base by Keizar'!G:G,'Movie Data Base by Keizar'!C:C,F22,'Movie Data Base by Keizar'!G:G,">0"),2),"") -> 6.14
A23: Aventura | B23: =COUNTIF('Movie Data Base by Keizar'!J:J,A23) -> 58 | C23: =COUNTIFS('Movie Data Base by Keizar'!J:J,A23,'Movie Data Base by Keizar'!G:G,">0") -> 29 | D23: =IFERROR(ROUND(AVERAGEIFS('Movie Data Base by Keizar'!G:G,'Movie Data Base by Keizar'!J:J,A23,'Movie Data Base by Keizar'!G:G,">0"),2),"") -> 6.17
A24: Documental | B24: =COUNTIF('Movie Data Base by Keizar'!J:J,A24) -> 33 | C24: =COUNTIFS('Movie Data Base by Keizar'!J:J,A24,'Movie Data Base by Keizar'!G:G,">0") -> 14 | D24: =IFERROR(ROUND(AVERAGEIFS('Movie Data Base by Keizar'!G:G,'Movie Data Base by Keizar'!J:J,A24,'Movie Data Base by Keizar'!G:G,">0"),2),"") -> 6.57
A25: Western | B25: =COUNTIF('Movie Data Base by Keizar'!J:J,A25) -> 19 | C25: =COUNTIFS('Movie Data Base by Keizar'!J:J,A25,'Movie Data Base by Keizar'!G:G,">0") -> 6 | D25: =IFERROR(ROUND(AVERAGEIFS('Movie Data Base by Keizar'!G:G,'Movie Data Base by Keizar'!J:J,A25,'Movie Data Base by Keizar'!G:G,">0"),2),"") -> 7.5
A30: PAÍSES MÁS VISTOS | F30: CANON PENDIENTE
A31: País | B31: En lista | C31: Vistas | F31: Sight & Sound: en lista | G31: =COUNT('Movie Data Base by Keizar'!T2:T4000) -> 253
A32: EE.UU. | B32: =COUNTIF('Movie Data Base by Keizar'!I:I,"*"&A32&"*") -> 1415 | C32: =COUNTIFS('Movie Data Base by Keizar'!I:I,"*"&A32&"*",'Movie Data Base by Keizar'!G:G,">0") -> 1047 | F32: Sight & Sound: vistas | G32: =COUNTIFS('Movie Data Base by Keizar'!T2:T4000,">0",'Movie Data Base by Keizar'!G2:G4000,">0") -> 29
A33: Reino Unido | B33: =COUNTIF('Movie Data Base by Keizar'!I:I,"*"&A33&"*") -> 297 | C33: =COUNTIFS('Movie Data Base by Keizar'!I:I,"*"&A33&"*",'Movie Data Base by Keizar'!G:G,">0") -> 174 | F33: Ranking J.Wild: en lista | G33: =COUNTA('Movie Data Base by Keizar'!V2:V4000) -> 449
A34: Francia | B34: =COUNTIF('Movie Data Base by Keizar'!I:I,"*"&A34&"*") -> 299 | C34: =COUNTIFS('Movie Data Base by Keizar'!I:I,"*"&A34&"*",'Movie Data Base by Keizar'!G:G,">0") -> 73 | F34: Ranking J.Wild: vistas | G34: =COUNTIFS('Movie Data Base by Keizar'!V2:V4000,"<>",'Movie Data Base by Keizar'!G2:G4000,">0") -> 100
A35: España | B35: =COUNTIF('Movie Data Base by Keizar'!I:I,"*"&A35&"*") -> 195 | C35: =COUNTIFS('Movie Data Base by Keizar'!I:I,"*"&A35&"*",'Movie Data Base by Keizar'!G:G,">0") -> 110 | F35: Top 150 XXI: vistas | G35: =COUNTIFS('Movie Data Base by Keizar'!W2:W4000,">0",'Movie Data Base by Keizar'!G2:G4000,">0") -> 0
A36: Alemania | B36: =COUNTIF('Movie Data Base by Keizar'!I:I,"*"&A36&"*") -> 186 | C36: =COUNTIFS('Movie Data Base by Keizar'!I:I,"*"&A36&"*",'Movie Data Base by Keizar'!G:G,">0") -> 91
A37: Japón | B37: =COUNTIF('Movie Data Base by Keizar'!I:I,"*"&A37&"*") -> 112 | C37: =COUNTIFS('Movie Data Base by Keizar'!I:I,"*"&A37&"*",'Movie Data Base by Keizar'!G:G,">0") -> 21
A38: Italia | B38: =COUNTIF('Movie Data Base by Keizar'!I:I,"*"&A38&"*") -> 97 | C38: =COUNTIFS('Movie Data Base by Keizar'!I:I,"*"&A38&"*",'Movie Data Base by Keizar'!G:G,">0") -> 25
A39: Canadá | B39: =COUNTIF('Movie Data Base by Keizar'!I:I,"*"&A39&"*") -> 89 | C39: =COUNTIFS('Movie Data Base by Keizar'!I:I,"*"&A39&"*",'Movie Data Base by Keizar'!G:G,">0") -> 62
A40: Corea del Sur | B40: =COUNTIF('Movie Data Base by Keizar'!I:I,"*"&A40&"*") -> 36 | C40: =COUNTIFS('Movie Data Base by Keizar'!I:I,"*"&A40&"*",'Movie Data Base by Keizar'!G:G,">0") -> 8
A41: China | B41: =COUNTIF('Movie Data Base by Keizar'!I:I,"*"&A41&"*") -> 42 | C41: =COUNTIFS('Movie Data Base by Keizar'!I:I,"*"&A41&"*",'Movie Data Base by Keizar'!G:G,">0") -> 23
A42: Argentina | B42: =COUNTIF('Movie Data Base by Keizar'!I:I,"*"&A42&"*") -> 44 | C42: =COUNTIFS('Movie Data Base by Keizar'!I:I,"*"&A42&"*",'Movie Data Base by Keizar'!G:G,">0") -> 10
A43: Dinamarca | B43: =COUNTIF('Movie Data Base by Keizar'!I:I,"*"&A43&"*") -> 35 | C43: =COUNTIFS('Movie Data Base by Keizar'!I:I,"*"&A43&"*",'Movie Data Base by Keizar'!G:G,">0") -> 3
A44: Australia | B44: =COUNTIF('Movie Data Base by Keizar'!I:I,"*"&A44&"*") -> 30 | C44: =COUNTIFS('Movie Data Base by Keizar'!I:I,"*"&A44&"*",'Movie Data Base by Keizar'!G:G,">0") -> 24
A45: México | B45: =COUNTIF('Movie Data Base by Keizar'!I:I,"*"&A45&"*") -> 22 | C45: =COUNTIFS('Movie Data Base by Keizar'!I:I,"*"&A45&"*",'Movie Data Base by Keizar'!G:G,">0") -> 7
A60: CÓMO LEER LOS COLORES
A61: Mi nota / IMDb | B61: Escala de color: rojo = bajo, amarillo = medio, verde = alto
A62: Votos / Puntos premios / Emmys | B62: Barra proporcional: cuanto más llena, mayor el valor
A63: Título en dorado | B63: Pendiente de ver y con muchos premios: prioridad alta
A64: Título en verde | B64: Está en el top 100 de Sight & Sound (canon crítico)
A65: Duración en rojo | B65: Dura 180 minutos o más
A66: Tipo en azul (Series) | B66: Es una miniserie, no una serie de temporadas
A67: Texto gris y cursiva | B67: Ya la has visto (tiene tu nota): puedes saltártela al buscar algo nuevo
